Workbook

Sheet Read Me
A1: PracticeLab — Ideal Chart Composition by Topic
A2: Inventory classification for chart identification and sourcing · built 15 October 2026
B5: What this workbook is
B6: The topic layer beneath the Coverage Matrix in PracticeLab_HC.xlsx. The HC model answers how many charts each specialty needs and what the team costs. It does not say which charts. This does: for every specialty it names the topics the pool must contain, the share of the pool each topic should hold, and the resulting target count.
B7: It is a classification taxonomy, not an inventory. No chart is listed here. It is the standard a sourced chart is classified against and the yardstick a gap report is measured by.
B9: Its relationship to the HC model
B10: Baseline chart pools | C10: Typed once, on Specialty Summary, from the HC Specialty Grid (Baseline Charts Required, +10% buffer). Change a pool there and every topic target reflows.
B11: Parent percentages | C11: Carried from HC Chart Selection section 6 (Coverage Matrix) unchanged. Topic weights decompose a parent and sum back to it exactly — the TOTAL row on each sheet proves it.
B12: Difficulty mix | C12: HC section 4 sets 40% Basic / 40% Moderate / 20% Complex across the pool. Applied at specialty level on Specialty Summary. Each topic carries a skew instead, because a topic such as critical care cannot hold a Basic-tier chart.
B13: Sourcing channels | C13: The C1–C8 codes are HC section 3. Each topic names the channel most likely to yield it, so a gap in a topic points at a report to pull from.
B14: Required tags | C14: HC section 7 lists eight mandatory tags per chart. The Tag Dictionary sheet repeats them and adds the Topic ID this workbook introduces, which is the field that makes a topic-level gap report possible at all.
B16: How to use it
B17: Sourcing | C17: Read Target Charts as the ceiling for a topic. Once it is filled, further charts in that topic displace coverage elsewhere, however good they are.
B18: Classifying | C18: Every chart entering the pool gets exactly one Topic ID. A chart that genuinely spans two topics is classified by the element its answer key turns on.
B19: Gap review | C19: Count live charts per Topic ID against Target Charts. HC section 9 sets the trigger at 80% of target, reviewed monthly and at each half-yearly refresh.
B20: Changing a weight | C20: Edit the Topic % cell (shaded). The target recalculates and the TOTAL row will stop reading 100% until the other weights in that parent category are rebalanced. That is the point — the sheet refuses to let a topic quietly grow.
B21: Build priority | C21: P1 (build first) to P4 (build last) per topic, in a column of its own, because priority and volume are different questions. The weight says how many charts a topic should hold once the pool is complete; the priority says which topics are sourced and built before it is. IP-DRG leads with the OB and newborn block across both medical and surgical DRGs, then GI, respiratory and cardiovascular. E/M leads with level 3 and 4 office visits and the inpatient and observation trio.
B23: The four populations are separate
B24: ED Facility, ED Profee, ED Single Path and E/M are four distinct chart populations, confirmed on 15 October 2026. The same clinical encounter coded for the facility, coded professionally, and coded single-path produces three different charts, and none of them sits in the E/M pool. Their pools therefore add rather than overlap, and the E/M topic list holding no ED setting is deliberate.
B25: The consequence for sourcing is the part worth saying out loud: four populations means four separate pulls, not one pull classified four ways. A chart cannot be filed under an ED Facility topic and an ED Profee topic at once, and reusing one encounter across two pools would put the same documentation in front of a coder twice under two different names.
B27: What the targets are and are not
B28: A target is a proportion of a pool, not a forecast of what production will yield. Where the two disagree the pool is wrong, not the sheet: a pool that drifts toward whatever charts were easy to find teaches whatever those charts happened to contain.
B29: Rounding is per topic, so the sum of targets can differ from the pool by a chart or two. Each sheet shows the variance rather than hiding it, and the pool is the authority.
B31: Scope
B32: Seven specialties. IP-DRG, ED Facility, E/M and SDS carry HC baseline pools. ED Profee, Surgery and ED Single Path each carry a pool set on 15 October 2026 (400, 300 and 300) rather than one derived in the HC model. Denials/Edits and Ancillary are deferred — their HC pools and coverage matrices stand, and a topic layer for them is the obvious next addition.
B33: Open questions that need a decision before this is final are on the Open Decisions sheet. They are listed rather than resolved because each changes a number somebody else owns.

Sheet Specialty Summary
A1: Specialty Summary — baseline pools and difficulty mix
A2: Pools are the only hand-typed counts in this workbook. Shaded cells are inputs; everything else is a formula.
A4: Specialty | B4: Type | C4: Baseline Chart Pool | D4: % of Total Pool | E4: Topics Defined | F4: Allocated by Topic | G4: Variance (rounding) | H4: Basic (40%) | I4: Moderate (40%) | J4: Complex (20%) | K4: Pool source
A5: IP-DRG | B5: IP | C5: 693 | D5: =C5/$C$12 | E5: ='IP-DRG Topics'!$D$2 | F5: ='IP-DRG Topics'!$F$2 | G5: =F5-C5 | H5: =ROUND(C5*0.4,0) | I5: =ROUND(C5*0.4,0) | J5: =ROUND(C5*0.2,0) | K5: HC Specialty Grid
A6: ED Facility | B6: OP | C6: 704 | D6: =C6/$C$12 | E6: ='ED Facility Topics'!$D$2 | F6: ='ED Facility Topics'!$F$2 | G6: =F6-C6 | H6: =ROUND(C6*0.4,0) | I6: =ROUND(C6*0.4,0) | J6: =ROUND(C6*0.2,0) | K6: HC Specialty Grid
A7: ED Profee | B7: OP | C7: 400 | D7: =C7/$C$12 | E7: ='ED Profee Topics'!$D$2 | F7: ='ED Profee Topics'!$F$2 | G7: =F7-C7 | H7: =ROUND(C7*0.4,0) | I7: =ROUND(C7*0.4,0) | J7: =ROUND(C7*0.2,0) | K7: Set 2026-10-15; no HC row yet
A8: E/M | B8: OP | C8: 413 | D8: =C8/$C$12 | E8: ='E-M Topics'!$D$2 | F8: ='E-M Topics'!$F$2 | G8: =F8-C8 | H8: =ROUND(C8*0.4,0) | I8: =ROUND(C8*0.4,0) | J8: =ROUND(C8*0.2,0) | K8: HC Specialty Grid
A9: SDS | B9: OP | C9: 132 | D9: =C9/$C$12 | E9: ='SDS Topics'!$D$2 | F9: ='SDS Topics'!$F$2 | G9: =F9-C9 | H9: =ROUND(C9*0.4,0) | I9: =ROUND(C9*0.4,0) | J9: =ROUND(C9*0.2,0) | K9: HC Specialty Grid
A10: Surgery | B10: OP | C10: 300 | D10: =C10/$C$12 | E10: ='Surgery Topics'!$D$2 | F10: ='Surgery Topics'!$F$2 | G10: =F10-C10 | H10: =ROUND(C10*0.4,0) | I10: =ROUND(C10*0.4,0) | J10: =ROUND(C10*0.2,0) | K10: Set 2026-10-15; no HC row yet
A11: ED Single Path | B11: OP | C11: 300 | D11: =C11/$C$12 | E11: ='ED Single Path Topics'!$D$2 | F11: ='ED Single Path Topics'!$F$2 | G11: =F11-C11 | H11: =ROUND(C11*0.4,0) | I11: =ROUND(C11*0.4,0) | J11: =ROUND(C11*0.2,0) | K11: Set 2026-10-15; no HC row yet
A12: TOTAL | C12: =SUM(C5:C11) | D12: =SUM(D5:D11) | E12: =SUM(E5:E11) | F12: =SUM(F5:F11) | G12: =SUM(G5:G11) | H12: =SUM(H5:H11) | I12: =SUM(I5:I11) | J12: =SUM(J5:J11)
A14: Difficulty columns apply the pool-level 40 / 40 / 20 mix from HC Chart Selection section 4. They are a specialty-level target: no single topic is required to hold that mix, and some topics cannot (critical care has no Basic-tier chart; a routine lab has no Complex one). Each topic sheet carries a skew column instead.
A15: Variance is the rounding drift between the sum of topic targets and the pool. The pool is the authority; a variance of more than a few charts means a topic weight was edited without rebalancing its parent category.
A16: Three specialties sit outside the HC model: ED Profee (400), Surgery (300) and ED Single Path (300). Each has a pool but none has the +10% buffer calculation, batch count or build-hour line the other four get from the HC Specialty Grid. That is 1,000 charts the HC model does not know about — at its own build rates roughly 1,500 to 2,250 build hours, close to a further FTE. The Specialty Grid, Chart Pool and FTE sheets understate until all three are added there.

Sheet IP-DRG Topics
A1: IP-DRG — ideal chart composition by topic
A2: Baseline pool | B2: ='Specialty Summary'!$C$5 | C2: Topics | D2: =COUNTA(A5:A31)-2 | E2: Allocated | F2: =SUM(G5:G31) | G2: Variance | H2: =F2-B2 | I2: Dimension: DRG type
A4: Topic ID | B4: Coverage category | C4: Topic | D4: Scope — what counts here | E4: Not here (goes where instead) | F4: Topic % of pool | G4: Target charts | H4: Build priority | I4: Difficulty skew | J4: Primary sourcing channel | K4: Key elements the chart must exercise | L4: Notes
A5: MEDICAL DRGS — HC Coverage Matrix parent: 55% | F5: =IF(ROUND(SUMIF($B$5:$B$31,"Medical DRGs",$F$5:$F$31),6)=0.55,"OK — topics sum to the 55% parent","CHECK — topics do not sum to the 55% parent")
A6: IPD-01 | B6: Medical DRGs | C6: Vaginal delivery and complications of labour | D6: Delivery admissions grouping medical: vaginal and assisted delivery, complications of labour, and the maternal record only. | E6: Caesarean delivery — IPD-15; the newborn record — IPD-02 | F6: 0.05 | G6: =ROUND(F6*$B$2,0) | H6: P1 | I6: Complex-led | J6: C6 Customer escalations | K6: Principal diagnosis for a delivery admission, Z3A gestational weeks, outcome-of-delivery code, PCS delivery root operation, CC/MCC capture | L6: The PDx for a delivery admission is the complication, not the delivery — the error that keeps recurring. Vaginal delivery groups MEDICAL and caesarean groups SURGICAL, so OB sits on both sides of the 55/45 split and must be sourced against both.
A7: IPD-02 | B7: Medical DRGs | C7: Normal newborn and newborn with condition | D7: The newborn record: normal newborn, newborn with a condition identified after birth, and the birth-weight and gestational-age axes that drive grouping. | E7: The maternal record — IPD-01 or IPD-15 | F7: 0.04 | G7: =ROUND(F7*$B$2,0) | H7: P1 | I7: Moderate-led | J7: C1 High error rate | K7: Birth weight, gestational age, newborn condition coding, POA on a newborn record, liveborn versus condition sequencing | L7: Mother and newborn records are linked; HC rule R3 requires PHI scrubbed from both before either is used. Birth weight is entered in grams and is the single most consequential value on the record.
A8: IPD-03 | B8: Medical DRGs | C8: Neonatal and NICU admissions | D8: Prematurity, low birth weight, respiratory distress of the newborn, and neonatal admissions whose DRG turns on weight bands and procedures. | E8: — | F8: 0.02 | G8: =ROUND(F8*$B$2,0) | H8: P1 | I8: Complex-led | J8: C2 High dollar value | K8: Birth-weight band boundaries, prematurity coding, ventilator hours on a neonate, POA, MCC capture | L8: The weight bands are hard boundaries: a hundred grams moves the DRG. High dollar value and high error rate at once.
A9: IPD-04 | B9: Medical DRGs | C9: Antepartum and postpartum medical admissions | D9: Maternal admissions that are not the delivery: hyperemesis, pre-eclampsia, preterm labour not delivered, and postpartum complications managed medically. | E9: Postpartum surgical procedures — IPD-16 | F9: 0.02 | G9: =ROUND(F9*$B$2,0) | H9: P1 | I9: Complex-led | J9: C1 High error rate | K9: Trimester characters, delivered versus not delivered, postpartum period rules, PDx selection, Z3A | L9: The not-delivered admissions are where the trimester character and the delivered/undelivered distinction go wrong.
A10: IPD-05 | B10: Medical DRGs | C10: Digestive medical — GI bleed, pancreatitis, obstruction | D10: Medical GI admissions: GI haemorrhage with and without a stated site, pancreatitis aetiology, obstruction managed conservatively. | E10: Bowel resection, cholecystectomy and hernia repair — IPD-17 | F10: 0.06 | G10: =ROUND(F10*$B$2,0) | H10: P2 | I10: Moderate-led | J10: C1 High error rate | K10: Bleeding site specificity, aetiology linkage, blood transfusion capture, CC/MCC, PDx sequencing
A11: IPD-06 | B11: Medical DRGs | C11: Respiratory — pneumonia, COPD exacerbation, respiratory failure | D11: Admissions where the principal diagnosis is respiratory and no OR procedure drives the DRG. Includes acute-on-chronic respiratory failure and the ventilator-hours boundary. | E11: Thoracotomy and tracheostomy cases — IPD-19 | F11: 0.07 | G11: =ROUND(F11*$B$2,0) | H11: P2 | I11: Moderate-led | J11: C1 High error rate | K11: Principal diagnosis selection, pneumonia organism specificity, CC/MCC capture, POA, ventilator hours | L11: Sequencing respiratory failure against the underlying condition is the most disputed PDx call in this specialty. Carry charts in both directions.
A12: IPD-07 | B12: Medical DRGs | C12: Circulatory medical — heart failure, AMI, arrhythmia | D12: Medical cardiac admissions. Heart failure type and acuity, AMI type 1 versus type 2, atrial fibrillation. | E12: CABG, valve, PCI and EP procedures — IPD-18 | F12: 0.06 | G12: =ROUND(F12*$B$2,0) | H12: P2 | I12: Moderate-led | J12: C5 DRGV trending PCS / DRG | K12: Heart failure specificity, AMI type, CC/MCC capture, PDx sequencing when cardiac and respiratory both present | L12: Type 2 MI versus demand ischaemia is a current trending error area; refresh from the DRGV report each cycle.
A13: IPD-08 | B13: Medical DRGs | C13: Sepsis, severe sepsis and septic shock | D13: Sepsis as principal or secondary, with and without organ dysfunction. Includes the localised-infection-versus-sepsis judgement and post-procedural sepsis. | E13: Newborn sepsis — IPD-02 or IPD-03 | F13: 0.07 | G13: =ROUND(F13*$B$2,0) | H13: P2 | I13: Complex-led | J13: C1 High error rate | K13: Sepsis sequencing, severe sepsis with organ dysfunction, R65.2x, POA, query opportunity, MCC capture | L13: Highest-yield topic for query practice (HC use case 07). Charts with a resolved query are preferred; unresolved ones are excluded by X3.
A14: IPD-09 | B14: Medical DRGs | C14: Nervous system medical — CVA, TIA, intracranial haemorrhage | D14: Acute neurological admissions coded medically, including thrombolytic administration and residual-deficit codes. | E14: Craniotomy, shunt and spine decompression — IPD-21 | F14: 0.04 | G14: =ROUND(F14*$B$2,0) | H14: P2 | I14: Complex-led | J14: C2 High dollar value | K14: CVA site and laterality, late effect versus acute, thrombolytic status Z92.82, POA, functional deficit capture | L14: Z92.82 affects the DRG and is routinely missed when the thrombolytic was given at a transferring facility.
A15: IPD-10 | B15: Medical DRGs | C15: Kidney and urinary — AKI, CKD, UTI | D15: Renal admissions with no OR procedure. Includes AKI on CKD, the AKI-versus-dehydration call, and dialysis dependence. | E15: Dialysis access creation and nephrectomy — IPD-22 | F15: 0.03 | G15: =ROUND(F15*$B$2,0) | H15: P2 | I15: Moderate-led | J15: C1 High error rate | K15: AKI versus CKD staging, N17/N18 combination, CC/MCC capture, POA | L15: AKI is a CC and is often documented only as a lab trend; a strong query topic.
A16: IPD-11 | B16: Medical DRGs | C16: Endocrine and metabolic — DKA, malnutrition, electrolyte disorders | D16: Diabetic emergencies, severe protein-calorie malnutrition, and significant electrolyte disturbance as principal or as the MCC. | E16: — | F16: 0.03 | G16: =ROUND(F16*$B$2,0) | H16: P2 | I16: Complex-led | J16: C1 High error rate | K16: Diabetes with complication linkage, malnutrition severity and clinical criteria, MCC capture, POA | L16: Severe malnutrition is a high-value MCC and the most commonly denied on audit; the chart must carry the clinical criteria, not just the dietitian note.
A17: IPD-12 | B17: Medical DRGs | C17: Haematology and oncology — medical admissions | D17: Neutropenia, anaemia requiring transfusion, sickle-cell crisis, and admissions for a complication of a malignancy. | E17: Admissions for chemotherapy administration alone — out of scope this cycle | F17: 0.03 | G17: =ROUND(F17*$B$2,0) | H17: P2 | I17: Complex-led | J17: C6 Customer escalations | K17: Neoplasm versus complication sequencing, primary versus secondary site, admission-for-treatment rules, anaemia in neoplastic disease | L17: Sequencing an admission for a complication of cancer against the cancer itself is a recurring escalation topic.
A18: IPD-13 | B18: Medical DRGs | C18: Mental health and substance use | D18: Psychiatric and substance-withdrawal admissions where the full record is available for training use. | E18: Anything under 42 CFR Part 2 or client-restricted — removed entirely by X2 | F18: 0.02 | G18: =ROUND(F18*$B$2,0) | H18: P3 | I18: Basic-led | J18: C8 Foundation | K18: Substance use versus abuse versus dependence, withdrawal with complication, psychiatric PDx selection | L18: Sourcing is narrow by design: X2 removes most candidates. If eligible supply is not there, report it as a constrained topic rather than forcing the target.
A19: IPD-14 | B19: Medical DRGs | C19: Other infectious disease | D19: Infectious admissions that are not sepsis: cellulitis, osteomyelitis, C. difficile, endocarditis, and device-related infection. | E19: Sepsis and septic shock — IPD-08 | F19: 0.01 | G19: =ROUND(F19*$B$2,0) | H19: P3 | I19: Moderate-led | J19: C8 Foundation | K19: Organism specificity, device-related infection coding, PDx sequencing against the device complication, CC/MCC | L19: Device-related infection carries a complication code that must be sequenced with the infection; a frequent miss.
A20: SURGICAL DRGS — HC Coverage Matrix parent: 45% | F20: =IF(ROUND(SUMIF($B$5:$B$31,"Surgical DRGs",$F$5:$F$31),6)=0.45,"OK — topics sum to the 45% parent","CHECK — topics do not sum to the 45% parent")
A21: IPD-15 | B21: Surgical DRGs | C21: Caesarean delivery | D21: Caesarean delivery admissions, which group surgical, including the indication that drives the principal diagnosis and sterilisation performed at the same time. | E21: Vaginal delivery — IPD-01; the newborn record — IPD-02 | F21: 0.04 | G21: =ROUND(F21*$B$2,0) | H21: P1 | I21: Complex-led | J21: C1 High error rate | K21: Principal diagnosis (the indication, not the caesarean), PCS delivery root operation and approach, concurrent sterilisation, Z3A, CC/MCC | L21: The caesarean half of the OB priority block. Coding the caesarean itself as the PDx instead of the indication is the error this topic exists to train.
A22: IPD-16 | B22: Surgical DRGs | C22: Obstetric and postpartum surgical procedures | D22: Postpartum haemorrhage requiring intervention, retained products with D&C, obstetric laceration repair, and hysterectomy for an obstetric cause. | E22: Antepartum and postpartum medical admissions — IPD-04 | F22: 0.02 | G22: =ROUND(F22*$B$2,0) | H22: P1 | I22: Complex-led | J22: C6 Customer escalations | K22: PCS root operation for evacuation and repair, postpartum period rules, PDx sequencing, blood product capture | L22: Low volume, high error rate. Completes the OB priority block on the surgical side.
A23: IPD-17 | B23: Surgical DRGs | C23: Digestive surgical — bowel resection, cholecystectomy, hernia repair | D23: Inpatient abdominal surgery, including laparoscopic-to-open conversion and anastomosis as a separate root operation. | E23: Same-day general surgery — SDS-12 | F23: 0.08 | G23: =ROUND(F23*$B$2,0) | H23: P2 | I23: Moderate-led | J23: C8 Foundation | K23: Root operation selection (Excision versus Resection), approach character, conversion coding, post-operative complication with POA | L23: Excision versus Resection on a partial organ is the classic PCS error and is worth planting in both directions.
A24: IPD-18 | B24: Surgical DRGs | C24: Cardiovascular surgical — CABG, valve, PCI, EP procedures | D24: Open and percutaneous cardiac procedures, including multi-vessel PCI with differing stent counts and intraoperative conversion. | E24: Diagnostic catheterisation with no intervention — out of scope this cycle | F24: 0.08 | G24: =ROUND(F24*$B$2,0) | H24: P2 | I24: Complex-led | J24: C2 High dollar value | K24: PCS body-part and device characters, number of sites treated, graft harvesting as a separate procedure, PDx sequencing | L24: Highest reimbursement per chart in the pool. Counting treated sites and graft harvest is where the PCS code goes wrong.
A25: IPD-19 | B25: Surgical DRGs | C25: Respiratory surgical — thoracotomy, tracheostomy, lung resection | D25: Thoracic surgery and tracheostomy, including tracheostomy performed during a long ventilator stay, which changes the DRG entirely. | E25: — | F25: 0.03 | G25: =ROUND(F25*$B$2,0) | H25: P2 | I25: Complex-led | J25: C5 DRGV trending PCS / DRG | K25: PCS root operation and approach, tracheostomy with ventilator hours, lobe-level body part, POA | L25: A tracheostomy on a ventilated patient moves the case to the highest-weight DRG family; missing it is a large-dollar error.
A26: IPD-20 | B26: Surgical DRGs | C26: Musculoskeletal — joint replacement, spinal fusion, fracture fixation | D26: Elective and traumatic MSK surgery requiring admission. Approach and device-value axes of the PCS code, fusion level counts. | E26: Same-day orthopaedic procedures — SDS-01 to SDS-03 | F26: 0.09 | G26: =ROUND(F26*$B$2,0) | H26: P2 | I26: Moderate-led | J26: C5 DRGV trending PCS / DRG | K26: PCS root operation and device character, fusion levels and approach, bilateral procedures, POA on post-operative conditions | L26: Highest-volume surgical family and the best place to train PCS character selection. Carries the device-value character the auditor module plants against.
A27: IPD-21 | B27: Surgical DRGs | C27: Nervous system surgical — craniotomy, shunt, spine decompression | D27: Cranial and spinal surgery including shunt revision, which is a different root operation from shunt insertion. | E27: — | F27: 0.04 | G27: =ROUND(F27*$B$2,0) | H27: P2 | I27: Complex-led | J27: C2 High dollar value | K27: PCS root operation on a device (Revision, Replacement, Removal), body-part character, laterality, POA | L27: Device-related root operations are the least familiar part of PCS and are most often coded as Insertion.
A28: IPD-22 | B28: Surgical DRGs | C28: Genitourinary surgical | D28: Nephrectomy, prostatectomy, dialysis access creation and urological procedures requiring admission. | E28: Cystoscopy and stone procedures done same-day — SDS-15 | F28: 0.03 | G28: =ROUND(F28*$B$2,0) | H28: P2 | I28: Moderate-led | J28: C8 Foundation | K28: PCS body-part laterality, approach character, CC/MCC capture
A29: IPD-23 | B29: Surgical DRGs | C29: Vascular access and device procedures — PICC, pacemaker, dialysis catheter | D29: Procedures whose DRG is driven by the device rather than the diagnosis, performed during a medical admission. | E29: — | F29: 0.02 | G29: =ROUND(F29*$B$2,0) | H29: P3 | I29: Moderate-led | J29: C6 Customer escalations | K29: PCS device and qualifier characters, central versus peripheral body part, Insertion versus Revision | L29: PICC lines are a named customer escalation area in the HC trainer-role sheet. Keep this topic filled.
A30: IPD-24 | B30: Surgical DRGs | C30: Transplant and other high-weight DRGs | D30: Solid-organ transplant, ECMO and other very high relative-weight cases. | E30: — | F30: 0.01 | G30: =ROUND(F30*$B$2,0) | H30: P3 | I30: Complex-led | J30: C2 High dollar value | K30: PCS transplant qualifier, ECMO coding, PDx sequencing, MCC capture | L30: Low volume by nature. One or two charts per refresh is the realistic supply; do not inflate the weight to force a count.
A31: IPD-25 | B31: Surgical DRGs | C31: Multiple significant trauma and burns | D31: Polytrauma and significant burn admissions, where sequencing rules are specific and code volume is high. | E31: Single-site injury seen in the ED — EDF-06 | F31: 0.01 | G31: =ROUND(F31*$B$2,0) | H31: P3 | I31: Complex-led | J31: C2 High dollar value | K31: Multiple significant trauma DRG criteria, burn TBSA coding, injury sequencing, POA
A32: TOTAL | F32: =SUM(F5:F31) | G32: =SUM(G5:G31) | H32: Weights must total 100%
A34: Shaded Topic %% cells are the only editable numbers on this sheet. Target charts recalculates from the pool on Specialty Summary. Edit a weight and the category check in its band row will read CHECK until the other weights in that category are rebalanced — the sheet is built to refuse a topic that quietly grows at its neighbours' expense.
A35: Target charts is a ceiling, not a quota to fill at any cost. Where eligible supply genuinely is not there — a topic narrowed by exclusion X2, or a low-volume case type — report it as constrained in the gap review rather than substituting charts from an adjacent topic.
A36: Variance in the strip above is rounding drift between the sum of topic targets and the pool. The pool is the authority.

Sheet ED Facility Topics
A1: ED Facility — ideal chart composition by topic
A2: Baseline pool | B2: ='Specialty Summary'!$C$6 | C2: Topics | D2: =COUNTA(A5:A25)-4 | E2: Allocated | F2: =SUM(G5:G25) | G2: Variance | H2: =F2-B2 | I2: Dimension: Facility level
A4: Topic ID | B4: Coverage category | C4: Topic | D4: Scope — what counts here | E4: Not here (goes where instead) | F4: Topic % of pool | G4: Target charts | H4: Build priority | I4: Difficulty skew | J4: Primary sourcing channel | K4: Key elements the chart must exercise | L4: Notes
A5: LEVELS 1–2 — HC Coverage Matrix parent: 20% | F5: =IF(ROUND(SUMIF($B$5:$B$25,"Levels 1–2",$F$5:$F$25),6)=0.2,"OK — topics sum to the 20% parent","CHECK — topics do not sum to the 20% parent")
A6: EDF-01 | B6: Levels 1–2 | C6: Minor presentations and rechecks (99281 / 99282) | D6: Low-acuity visits resolved with assessment and simple intervention: medication refill, suture removal, wound recheck, dressing change. | E6: — | F6: 0.1 | G6: =ROUND(F6*$B$2,0) | H6: P2 | I6: Basic-led | J6: C8 Foundation | K6: Facility level criteria and the point-based acuity tool, diagnosis specificity, discharge disposition | L6: The main source of Week 1 Basic-tier charts for ED. Keep this topic full or Week 1 has nothing to run on.
A7: EDF-02 | B7: Levels 1–2 | C7: Nurse-only and ancillary-only ED encounters | D7: Visits with no provider evaluation: injection-only, blood-draw-only, or ancillary service performed in the ED setting. | E7: Visits where a provider evaluated the patient — EDF-01 | F7: 0.05 | G7: =ROUND(F7*$B$2,0) | H7: P3 | I7: Basic-led | J7: C8 Foundation | K7: Whether a facility level is billable at all, ancillary-only service coding, diagnosis linkage | L7: Teaches the lower bound of the ladder: the correct answer is sometimes that no E/M level applies.
A8: EDF-03 | B8: Levels 1–2 | C8: Low-acuity visits with an ED procedure | D8: Simple procedure as the reason for the visit: foreign body removal, simple I&D, nail trephination. | E8: — | F8: 0.05 | G8: =ROUND(F8*$B$2,0) | H8: P2 | I8: Basic-led | J8: C1 High error rate | K8: Procedure versus facility level interaction, separately reportable service, laterality and site
A9: LEVEL 3 — HC Coverage Matrix parent: 30% | F9: =IF(ROUND(SUMIF($B$5:$B$25,"Level 3",$F$5:$F$25),6)=0.3,"OK — topics sum to the 30% parent","CHECK — topics do not sum to the 30% parent")
A10: EDF-04 | B10: Level 3 | C10: Moderate medical presentations — URI, UTI, gastroenteritis | D10: Common medical complaints with limited workup: one or two diagnostics, oral or single IV medication. | E10: — | F10: 0.1 | G10: =ROUND(F10*$B$2,0) | H10: P2 | I10: Basic-led | J10: C8 Foundation | K10: Facility level criteria, diagnosis specificity, medication administration capture
A11: EDF-05 | B11: Level 3 | C11: Minor trauma and wound repair | D11: Laceration repair by length and complexity, contusions, abrasions, and minor burns. | E11: Polytrauma — EDF-16 | F11: 0.08 | G11: =ROUND(F11*$B$2,0) | H11: P2 | I11: Moderate-led | J11: C1 High error rate | K11: Repair length and complexity tiers, anatomic site grouping, injury external cause, facility level | L11: Summing repair lengths across sites in the same anatomic group is the recurring error here.
A12: EDF-06 | B12: Level 3 | C12: Orthopaedic injury — sprain, simple fracture, splinting | D12: Extremity injury with imaging, splint or cast application, and reduction where performed. | E12: Injuries admitted for operative fixation — IP-DRG (IPD-20) | F12: 0.07 | G12: =ROUND(F12*$B$2,0) | H12: P2 | I12: Moderate-led | J12: C1 High error rate | K12: Fracture site and laterality, initial encounter character, splint and strapping application, facility level | L12: The seventh character for encounter type is the most frequently wrong element in this topic.
A13: EDF-07 | B13: Level 3 | C13: Infusion and injection administration visits | D13: ED visits where hydration, therapeutic infusion or injection is the substance of the encounter. | E13: — | F13: 0.05 | G13: =ROUND(F13*$B$2,0) | H13: P2 | I13: Moderate-led | J13: C7 Denial trends | K13: Infusion hierarchy (chemo, therapeutic, hydration), initial versus sequential versus concurrent, units by time, diagnosis linkage | L13: The infusion hierarchy and the start/stop time arithmetic are a denial-trend area; source from the denial report.
A14: LEVEL 4 — HC Coverage Matrix parent: 30% | F14: =IF(ROUND(SUMIF($B$5:$B$25,"Level 4",$F$5:$F$25),6)=0.3,"OK — topics sum to the 30% parent","CHECK — topics do not sum to the 30% parent")
A15: EDF-08 | B15: Level 4 | C15: Abdominal and chest pain workups | D15: Undifferentiated pain presentations with extensive diagnostics and serial assessment, discharged with a symptom diagnosis. | E15: — | F15: 0.09 | G15: =ROUND(F15*$B$2,0) | H15: P2 | I15: Moderate-led | J15: C1 High error rate | K15: Facility level criteria at the 4/5 boundary, symptom versus confirmed diagnosis, serial diagnostic capture | L15: Teaches coding to a symptom when no diagnosis was reached — the correct answer is often the symptom code.
A16: EDF-09 | B16: Level 4 | C16: Respiratory distress — asthma, COPD, pneumonia | D16: Respiratory presentations with nebuliser treatment, imaging, and sometimes non-invasive ventilation. | E16: Intubated or critical care patients — EDF-13 or EDF-14 | F16: 0.07 | G16: =ROUND(F16*$B$2,0) | H16: P2 | I16: Moderate-led | J16: C8 Foundation | K16: Exacerbation documentation, nebuliser and ventilation management capture, facility level, diagnosis specificity
A17: EDF-10 | B17: Level 4 | C17: Complex medical with multiple workups | D17: Multi-system presentations in comorbid patients: weakness, syncope, altered mental state, with broad workup. | E17: — | F17: 0.07 | G17: =ROUND(F17*$B$2,0) | H17: P2 | I17: Complex-led | J17: C1 High error rate | K17: Facility level at the 4/5 boundary, comorbidity capture, diagnosis sequencing, extent of workup | L17: The level 4 versus 5 call is the highest-volume error in ED facility coding; this topic exists to train the boundary.
A18: EDF-11 | B18: Level 4 | C18: Behavioural health presentations | D18: Psychiatric and substance-related ED visits with medical screening, sitter or restraint use, and disposition delay. | E18: Records under 42 CFR Part 2 or client-restricted — removed by X2 | F18: 0.04 | G18: =ROUND(F18*$B$2,0) | H18: P3 | I18: Moderate-led | J18: C6 Customer escalations | K18: Facility level where time and monitoring drive acuity, substance use coding, suicidal ideation coding, disposition | L18: Constrained supply under X2. Report as constrained rather than forcing the count.
A19: EDF-12 | B19: Level 4 | C19: Observation services initiated from the ED | D19: ED visit converting to observation: observation hours, the ED level alongside it, and the discharge-or-admit decision. | E19: Inpatient admissions — IP-DRG | F19: 0.03 | G19: =ROUND(F19*$B$2,0) | H19: P2 | I19: Complex-led | J19: C7 Denial trends | K19: Observation hour counting, whether the ED level is separately reportable, status determination, diagnosis supporting observation | L19: Observation hour counting is a denial-trend area and is routinely coded from the order time rather than the clock time.
A20: LEVEL 5 / CRITICAL CARE — HC Coverage Matrix parent: 20% | F20: =IF(ROUND(SUMIF($B$5:$B$25,"Level 5 / critical care",$F$5:$F$25),6)=0.2,"OK — topics sum to the 20% parent","CHECK — topics do not sum to the 20% parent")
A21: EDF-13 | B21: Level 5 / critical care | C21: High-acuity medical (99285) | D21: Patients with immediate threat requiring extensive evaluation and intervention, short of critical care. | E21: Encounters where critical care time was documented — EDF-14 | F21: 0.06 | G21: =ROUND(F21*$B$2,0) | H21: P2 | I21: Complex-led | J21: C1 High error rate | K21: Facility level 5 criteria, extent of intervention, diagnosis specificity, comorbidity capture
A22: EDF-14 | B22: Level 5 / critical care | C22: Critical care (99291 / 99292) | D22: Encounters with documented critical care time and organ-system failure, including the bundled-service list and the facility charge alongside it. | E22: Level 5 visits with no documented critical care time — EDF-13; arguable cases — EDF-15 | F22: 0.08 | G22: =ROUND(F22*$B$2,0) | H22: P2 | I22: Complex-led | J22: C2 High dollar value | K22: Critical care qualification, time documentation, bundled versus separately reportable procedures, facility level interaction, revenue code use | L22: The largest critical care topic in any pool, because this is where the volume actually is. Whether the condition qualifies as critical care at all is the hardest question in the ED; the time arithmetic is not the training point and critical care time is never planted.
A23: EDF-15 | B23: Level 5 / critical care | C23: The level 5 versus critical care boundary | D23: Facility encounters sitting on the line: high-acuity patients where whether critical care was delivered at all is genuinely arguable on the record. | E23: Clear-cut critical care — EDF-14; clear-cut level 5 — EDF-13 | F23: 0.02 | G23: =ROUND(F23*$B$2,0) | H23: P2 | I23: Complex-led | J23: C6 Customer escalations | K23: Critical care qualification against the facility acuity tool, organ system failure, what the record must show, the resulting facility level | L23: The facility-side twin of EDP-07. A generated error cannot invent this call, so these charts earn their place by being argued rather than planted.
A24: EDF-16 | B24: Level 5 / critical care | C24: Trauma activation | D24: Encounters meeting the trauma team activation criteria, with the activation charge and its documentation requirements. | E24: — | F24: 0.02 | G24: =ROUND(F24*$B$2,0) | H24: P2 | I24: Complex-led | J24: C7 Denial trends | K24: Trauma activation criteria and pre-notification requirement, revenue code use, injury coding, facility level | L24: The activation charge requires pre-hospital notification; charts missing it teach the denial.
A25: EDF-17 | B25: Level 5 / critical care | C25: Cardiac arrest and resuscitation | D25: Resuscitation encounters including CPR, defibrillation, intubation and death in the department. | E25: — | F25: 0.02 | G25: =ROUND(F25*$B$2,0) | H25: P3 | I25: Complex-led | J25: C2 High dollar value | K25: Resuscitation procedure coding, critical care interaction, disposition including expired, diagnosis sequencing | L25: Resuscitation and critical care are reported together more often than not, so this topic is read alongside EDF-14 rather than instead of it.
A26: TOTAL | F26: =SUM(F5:F25) | G26: =SUM(G5:G25) | H26: Weights must total 100%
A28: Shaded Topic %% cells are the only editable numbers on this sheet. Target charts recalculates from the pool on Specialty Summary. Edit a weight and the category check in its band row will read CHECK until the other weights in that category are rebalanced — the sheet is built to refuse a topic that quietly grows at its neighbours' expense.
A29: Target charts is a ceiling, not a quota to fill at any cost. Where eligible supply genuinely is not there — a topic narrowed by exclusion X2, or a low-volume case type — report it as constrained in the gap review rather than substituting charts from an adjacent topic.
A30: Variance in the strip above is rounding drift between the sum of topic targets and the pool. The pool is the authority.

Sheet ED Profee Topics
A1: ED Profee — ideal chart composition by topic
A2: Baseline pool | B2: ='Specialty Summary'!$C$7 | C2: Topics | D2: =COUNTA(A5:A22)-6 | E2: Allocated | F2: =SUM(G5:G22) | G2: Variance | H2: =F2-B2 | I2: Dimension: ED E/M level
A4: Topic ID | B4: Coverage category | C4: Topic | D4: Scope — what counts here | E4: Not here (goes where instead) | F4: Topic % of pool | G4: Target charts | H4: Build priority | I4: Difficulty skew | J4: Primary sourcing channel | K4: Key elements the chart must exercise | L4: Notes
A5: LOW ACUITY — HC Coverage Matrix parent: 7% | F5: =IF(ROUND(SUMIF($B$5:$B$22,"Low acuity",$F$5:$F$22),6)=0.07,"OK — topics sum to the 7% parent","CHECK — topics do not sum to the 7% parent")
A6: EDP-01 | B6: Low acuity | C6: 99281 / 99282 — straightforward presentations | D6: Professional component of low-acuity ED visits: problem-focused history and examination, straightforward MDM. | E6: — | F6: 0.07 | G6: =ROUND(F6*$B$2,0) | H6: P2 | I6: Basic-led | J6: C8 Foundation | K6: MDM-based level selection, problem addressed, diagnosis specificity | L6: Graded on the ED ladder in services/em_levels.py, which is separate from the office ladders. Same level on the wrong ladder is a distinct error from a near miss on the right one.
A7: MODERATE — HC Coverage Matrix parent: 16% | F7: =IF(ROUND(SUMIF($B$5:$B$22,"Moderate",$F$5:$F$22),6)=0.16,"OK — topics sum to the 16% parent","CHECK — topics do not sum to the 16% parent")
A8: EDP-02 | B8: Moderate | C8: 99283 — moderate MDM | D8: Visits with limited data reviewed and low-to-moderate risk: one or two problems, limited diagnostics. | E8: — | F8: 0.1 | G8: =ROUND(F8*$B$2,0) | H8: P2 | I8: Basic-led | J8: C8 Foundation | K8: COPA, Data Review and Risk as three MDM levels, the 2-of-3 rule, diagnosis specificity | L8: MDM is audited as three levels, never as element ticks.
A9: EDP-03 | B9: Moderate | C9: 99283 with a separately reportable procedure | D9: Moderate visits where a minor procedure was performed and modifier 25 is in play. | E9: — | F9: 0.06 | G9: =ROUND(F9*$B$2,0) | H9: P2 | I9: Moderate-led | J9: C1 High error rate | K9: Modifier 25 appropriateness, procedure versus E/M separation, MDM level, laterality | L9: Modifier 25 is the single most audited modifier in ED profee coding.
A10: LEVEL 4 — HC Coverage Matrix parent: 18% | F10: =IF(ROUND(SUMIF($B$5:$B$22,"Level 4",$F$5:$F$22),6)=0.18,"OK — topics sum to the 18% parent","CHECK — topics do not sum to the 18% parent")
A11: EDP-04 | B11: Level 4 | C11: 99284 — moderate-to-high MDM | D11: Multiple problems or extensive data review with moderate risk, including prescription drug management. | E11: — | F11: 0.12 | G11: =ROUND(F11*$B$2,0) | H11: P2 | I11: Moderate-led | J11: C1 High error rate | K11: COPA, Data Review, Risk, the 2-of-3 rule, prescription drug management as a risk element | L11: The 99284/99285 boundary carries the most level errors; plant in both directions so upcoding and downcoding both appear.
A12: EDP-05 | B12: Level 4 | C12: 99284 with fracture care or wound repair | D12: Level 4 visits with a procedure that has its own global period, so the E/M may or may not be separately reportable. | E12: — | F12: 0.06 | G12: =ROUND(F12*$B$2,0) | H12: P2 | I12: Complex-led | J12: C1 High error rate | K12: Global period of the procedure, modifier 25 and 57, procedure code selection, MDM level
A13: LEVEL 5 — HC Coverage Matrix parent: 21% | F13: =IF(ROUND(SUMIF($B$5:$B$22,"Level 5",$F$5:$F$22),6)=0.21,"OK — topics sum to the 21% parent","CHECK — topics do not sum to the 21% parent")
A14: EDP-06 | B14: Level 5 | C14: 99285 — high MDM | D14: High COPA with extensive data and high risk, short of critical care. | E14: Documented critical care time — EDP-08 | F14: 0.13 | G14: =ROUND(F14*$B$2,0) | H14: P2 | I14: Complex-led | J14: C1 High error rate | K14: COPA at the highest level, data categories, risk including decision for hospitalisation, the 2-of-3 rule
A15: EDP-07 | B15: Level 5 | C15: 99285 versus 99291 — the critical care boundary | D15: Charts sitting on the line: high-acuity patients where whether the condition qualified as critical care is genuinely arguable. | E15: Clear-cut critical care — EDP-08; clear-cut level 5 — EDP-06 | F15: 0.08 | G15: =ROUND(F15*$B$2,0) | H15: P2 | I15: Complex-led | J15: C6 Customer escalations | K15: Critical care qualification, organ system failure, time documentation, MDM level if not critical care | L15: The hardest question in the ED and the one a generated error cannot invent. These charts need AnswerKey.cc_boundary set to borderline before the auditor module will plant against them.
A16: CRITICAL CARE — HC Coverage Matrix parent: 20% | F16: =IF(ROUND(SUMIF($B$5:$B$22,"Critical care",$F$5:$F$22),6)=0.2,"OK — topics sum to the 20% parent","CHECK — topics do not sum to the 20% parent")
A17: EDP-08 | B17: Critical care | C17: 99291 / 99292 — critical care | D17: Professional critical care with documented time and organ-system failure, including the bundled-service list and the second-hour units. | E17: Critical care delivered on the floor or in the ICU — E/M (EM-20) | F17: 0.14 | G17: =ROUND(F17*$B$2,0) | H17: P2 | I17: Complex-led | J17: C2 High dollar value | K17: Critical care qualification, bundled procedures, diagnosis sequencing, same-day E/M by the same provider | L17: The second largest critical care topic after EDF-14, and weighted for the volume the ED actually sees. The 99292 unit count follows from the time and is not where coders go wrong; critical care time itself is never planted. An auditor validates the code, not the arithmetic.
A18: EDP-09 | B18: Critical care | C18: Critical care with separately reportable procedures | D18: Critical care encounters where a procedure outside the bundled list was performed — central line, chest tube, intubation, transvenous pacing. | E18: Procedures already bundled into critical care — EDP-08 | F18: 0.06 | G18: =ROUND(F18*$B$2,0) | H18: P2 | I18: Complex-led | J18: C2 High dollar value | K18: Which procedures the critical care code bundles and which it does not, modifier 25 and 59, procedure code selection, time excluded for separately reported work | L18: The bundled list is the whole question, and time spent on a separately reportable procedure cannot also count toward critical care time — a double-count coders make routinely.
A19: CROSS-CUTTING — HC Coverage Matrix parent: 18% | F19: =IF(ROUND(SUMIF($B$5:$B$22,"Cross-cutting",$F$5:$F$22),6)=0.18,"OK — topics sum to the 18% parent","CHECK — topics do not sum to the 18% parent")
A20: EDP-10 | B20: Cross-cutting | C20: ED procedures billed with an E/M | D20: Laceration repair, I&D, fracture care, joint reduction and foreign body removal alongside the ED E/M. | E20: — | F20: 0.1 | G20: =ROUND(F20*$B$2,0) | H20: P2 | I20: Moderate-led | J20: C1 High error rate | K20: Procedure code selection, modifier 25 and 59, bundling against the E/M, laterality and site
A21: EDP-11 | B21: Cross-cutting | C21: Observation and admission by the ED physician | D21: Encounters where the ED physician initiates observation or admits, and the service crosses code families. | E21: — | F21: 0.04 | G21: =ROUND(F21*$B$2,0) | H21: P2 | I21: Complex-led | J21: C7 Denial trends | K21: Which code family applies, same-day E/M rules, modifier 25, diagnosis supporting the status
A22: EDP-12 | B22: Cross-cutting | C22: Split / shared and teaching-physician documentation | D22: Encounters documented by a resident, APP or jointly, where attestation and substantive-portion rules decide what is billable. | E22: — | F22: 0.04 | G22: =ROUND(F22*$B$2,0) | H22: P3 | I22: Complex-led | J22: C6 Customer escalations | K22: Split/shared substantive portion, teaching physician attestation, modifier use, MDM level | L22: A documentation-rule topic rather than a code-selection one: the correct answer sometimes is that the service is not billable as documented.
A23: TOTAL | F23: =SUM(F5:F22) | G23: =SUM(G5:G22) | H23: Weights must total 100%
A25: Shaded Topic %% cells are the only editable numbers on this sheet. Target charts recalculates from the pool on Specialty Summary. Edit a weight and the category check in its band row will read CHECK until the other weights in that category are rebalanced — the sheet is built to refuse a topic that quietly grows at its neighbours' expense.
A26: Target charts is a ceiling, not a quota to fill at any cost. Where eligible supply genuinely is not there — a topic narrowed by exclusion X2, or a low-volume case type — report it as constrained in the gap review rather than substituting charts from an adjacent topic.
A27: Variance in the strip above is rounding drift between the sum of topic targets and the pool. The pool is the authority.

Sheet E-M Topics
A1: E/M — ideal chart composition by topic
A2: Baseline pool | B2: ='Specialty Summary'!$C$8 | C2: Topics | D2: =COUNTA(A5:A36)-9 | E2: Allocated | F2: =SUM(G5:G36) | G2: Variance | H2: =F2-B2 | I2: Dimension: Service family
A4: Topic ID | B4: Coverage category | C4: Topic | D4: Scope — what counts here | E4: Not here (goes where instead) | F4: Topic % of pool | G4: Target charts | H4: Build priority | I4: Difficulty skew | J4: Primary sourcing channel | K4: Key elements the chart must exercise | L4: Notes
A5: OFFICE / OUTPATIENT VISITS — HC Coverage Matrix parent: 42% | F5: =IF(ROUND(SUMIF($B$5:$B$36,"Office / outpatient visits",$F$5:$F$36),6)=0.42,"OK — topics sum to the 42% parent","CHECK — topics do not sum to the 42% parent")
A6: EM-01 | B6: Office / outpatient visits | C6: Level 3 established patient office visit (99213) | D6: Established-patient visits levelled at 3 on medical decision making: one stable chronic problem or a single acute uncomplicated one, limited data, low risk. | E6: New patients — EM-03; level 4 — EM-02 | F6: 0.1 | G6: =ROUND(F6*$B$2,0) | H6: P1 | I6: Basic-led | J6: C8 Foundation | K6: COPA for a stable chronic problem, Data Review, Risk, the 2-of-3 rule, diagnosis specificity | L6: With EM-02 this is the foundation of the whole specialty: the widest spread of complexity inside one code, which is what makes it the Week 1 workhorse. 99213 versus 99214 is the most common level error in outpatient coding, so carry charts that sit close to the line in both directions.
A7: EM-02 | B7: Office / outpatient visits | C7: Level 4 established patient office visit (99214) | D7: Established visits levelled at 4: two or more stable chronic conditions, or one with exacerbation, with prescription drug management or moderate risk. | E7: Level 5 — EM-05 | F7: 0.11 | G7: =ROUND(F7*$B$2,0) | H7: P1 | I7: Moderate-led | J7: C1 High error rate | K7: COPA, Data Review categories, Risk including prescription drug management, the 2-of-3 rule | L7: The largest single topic in the pool. Vary the complexity deliberately — a 99214 earned on risk alone reads very differently from one earned on data, and a coder who has only seen the second will downcode the first.
A8: EM-03 | B8: Office / outpatient visits | C8: Level 3 new patient office visit (99203) | D8: New-patient visits levelled at 3: a problem of low complexity, limited data, low risk. | E8: Established patients — EM-01 | F8: 0.05 | G8: =ROUND(F8*$B$2,0) | H8: P1 | I8: Basic-led | J8: C8 Foundation | K8: New versus established determination, COPA, Data Review, Risk, the 2-of-3 rule | L8: New-patient and established-patient office visits are separate ladders. Same level on the wrong ladder is the new-versus-established error, which is a different finding from a near miss on the right ladder.
A9: EM-04 | B9: Office / outpatient visits | C9: Level 4 new patient office visit (99204) | D9: New-patient visits levelled at 4: multiple problems or extensive data review with moderate risk. | E9: — | F9: 0.06 | G9: =ROUND(F9*$B$2,0) | H9: P1 | I9: Moderate-led | J9: C1 High error rate | K9: COPA for multiple or chronic problems, independent interpretation and external discussion as data, moderate risk, the 2-of-3 rule | L9: The three-year rule decides new versus established and is the element most often taken on trust from the registration screen rather than the record.
A10: EM-05 | B10: Office / outpatient visits | C10: Level 5 office visit, new and established (99205 / 99215) | D10: The top of both office ladders: high COPA, extensive data, high risk — severe exacerbation, threat to bodily function, or a decision for hospitalisation. | E10: Visits levelled by time rather than MDM — EM-07 | F10: 0.07 | G10: =ROUND(F10*$B$2,0) | H10: P2 | I10: Complex-led | J10: C2 High dollar value | K10: COPA at the highest level, data categories including independent interpretation, high risk such as drug therapy requiring intensive monitoring, decision for hospitalisation | L10: Runs 10-15% of production and carries the highest office reimbursement, so an error here costs more than anywhere else on the ladder. Weighted at 7% rather than the production share because the pool exists to train the hard calls, not to mirror the mix.
A11: EM-06 | B11: Office / outpatient visits | C11: Level 1-2 office visits (99202 / 99211 / 99212) | D11: The bottom of the ladders, including 99211 as the visit with no required provider evaluation. | E11: — | F11: 0.03 | G11: =ROUND(F11*$B$2,0) | H11: P3 | I11: Basic-led | J11: C8 Foundation | K11: Whether a billable E/M occurred at all, 99211 incident-to requirements, minimal COPA and risk | L11: 5-10% of production and deliberately held below that here: low error rate and low dollar value, so it earns a P3. Its real teaching value is the lower bound — sometimes the correct answer is that no E/M is billable.
A12: TIME-BASED AND PROLONGED SERVICES — HC Coverage Matrix parent: 4% | F12: =IF(ROUND(SUMIF($B$5:$B$36,"Time-based and prolonged services",$F$5:$F$36),6)=0.04,"OK — topics sum to the 4% parent","CHECK — topics do not sum to the 4% parent")
A13: EM-07 | B13: Time-based and prolonged services | C13: Visits levelled by time, and prolonged service add-ons (99417 / G2212) | D13: Visits where total time on the date of service decides the level rather than medical decision making, and the prolonged-service add-ons that attach to the highest level. | E13: — | F13: 0.04 | G13: =ROUND(F13*$B$2,0) | H13: P2 | I13: Complex-led | J13: C7 Denial trends | K13: What counts toward total time on the date of service, the time thresholds per code, add-on unit counting, MDM versus time as the basis | L13: These are the charts behind the HC Method split of 80% MDM and 20% time. Time-levelled visits are not graded on medical decision making at all, so applicable_weights drops the MDM weights and the form is resolved per chart. Deliberately a small share: the trainers asked for very few.
A14: PREVENTIVE AND WELLNESS — HC Coverage Matrix parent: 14% | F14: =IF(ROUND(SUMIF($B$5:$B$36,"Preventive and wellness",$F$5:$F$36),6)=0.14,"OK — topics sum to the 14% parent","CHECK — topics do not sum to the 14% parent")
A15: EM-08 | B15: Preventive and wellness | C15: Annual wellness visit — initial versus subsequent (G0438 / G0439) | D15: The Medicare AWV and the determination that trips most often: G0438 is once per lifetime, G0439 every year after, and the Initial Preventive Physical Examination is a third thing again. | E15: Commercial preventive medicine visits — EM-09 | F15: 0.05 | G15: =ROUND(F15*$B$2,0) | H15: P2 | I15: Moderate-led | J15: C7 Denial trends | K15: Initial versus subsequent determination, the once-per-lifetime rule, IPPE versus AWV, required elements, diagnosis coding for a wellness visit | L15: Billing G0438 for a patient who has had one before is a straight denial and a common one. The chart must carry enough history to make the determination answerable.
A16: EM-09 | B16: Preventive and wellness | C16: Preventive medicine visits, age-banded (99381-99397) | D16: Commercial preventive visits where the code is chosen by age band and by new versus established. | E16: Medicare AWV — EM-08 | F16: 0.04 | G16: =ROUND(F16*$B$2,0) | H16: P2 | I16: Basic-led | J16: C8 Foundation | K16: Age-band code selection, new versus established, required components, diagnosis coding | L16: Not graded on medical decision making: a preventive visit is off-ladder, so planting abstains and applicable_weights drops the MDM weights.
A17: EM-10 | B17: Preventive and wellness | C17: Preventive or AWV with a same-day problem visit | D17: A wellness or preventive visit where a problem was also addressed, so a separate E/M is reportable with modifier 25 — and the documentation has to support both. | E17: — | F17: 0.03 | G17: =ROUND(F17*$B$2,0) | H17: P2 | I17: Complex-led | J17: C1 High error rate | K17: Modifier 25 on the problem visit, splitting preventive from problem documentation, MDM for the problem portion only, patient liability consequence | L17: The hardest preventive question and the one payers audit. Carry charts where the second E/M is NOT supported as well as charts where it is — a coder who always bills both is as wrong as one who never does.
A18: EM-11 | B18: Preventive and wellness | C18: Screening and counselling services | D18: Depression, obesity, alcohol misuse, smoking cessation and similar screening and behavioural counselling services, usually alongside another visit. | E18: — | F18: 0.02 | G18: =ROUND(F18*$B$2,0) | H18: P2 | I18: Moderate-led | J18: C7 Denial trends | K18: Service-specific code and G-code selection, time thresholds for counselling, frequency limits, diagnosis linkage, bundling against the visit | L18: Frequency limits are the recurring denial: most of these have an annual or per-period cap and the record rarely states what was done before.
A19: OFFICE PROCEDURES WITH AN E/M — HC Coverage Matrix parent: 5% | F19: =IF(ROUND(SUMIF($B$5:$B$36,"Office procedures with an E/M",$F$5:$F$36),6)=0.05,"OK — topics sum to the 5% parent","CHECK — topics do not sum to the 5% parent")
A20: EM-12 | B20: Office procedures with an E/M | C20: Minor office procedures billed with an E/M | D20: Cerumen removal, lesion destruction, skin tag removal, simple biopsies, injections and similar minor procedures performed at a visit. | E20: — | F20: 0.05 | G20: =ROUND(F20*$B$2,0) | H20: P3 | I20: Moderate-led | J20: C1 High error rate | K20: Modifier 25 appropriateness, whether the E/M is separately identifiable from the procedure, procedure code selection by method and count, laterality and site | L20: The whole topic is one question: was there a separately identifiable E/M, or is the visit the procedure? Cerumen removal needs instrumentation rather than lavage to be the procedure code at all, which is where it most often goes wrong.
A21: CARE MANAGEMENT AND TRANSITIONAL CARE — HC Coverage Matrix parent: 5% | F21: =IF(ROUND(SUMIF($B$5:$B$36,"Care management and transitional care",$F$5:$F$36),6)=0.05,"OK — topics sum to the 5% parent","CHECK — topics do not sum to the 5% parent")
A22: EM-13 | B22: Care management and transitional care | C22: Transitional care management (99495 / 99496) | D22: TCM following a discharge: the interactive contact inside two business days, the face-to-face visit inside 7 or 14 days, and the MDM level that separates the two codes. | E22: — | F22: 0.03 | G22: =ROUND(F22*$B$2,0) | H22: P3 | I22: Complex-led | J22: C7 Denial trends | K22: Interactive contact timing, face-to-face visit window, moderate versus high MDM, the 30-day service period, what may not be billed alongside | L22: Date arithmetic decides the code and the service period blocks other billing, so TCM is where a correct clinical read still produces a wrong claim.
A23: EM-14 | B23: Care management and transitional care | C23: Chronic care management (99490 / 99439 / 99487) | D23: CCM: the clinical staff time per calendar month, the care plan, consent, and the add-on codes for additional time. | E23: — | F23: 0.02 | G23: =ROUND(F23*$B$2,0) | H23: P4 | I23: Moderate-led | J23: C7 Denial trends | K23: Time thresholds per calendar month, add-on unit counting, care plan and consent requirements, two chronic conditions, concurrent billing restrictions | L23: Lowest priority in the specialty: real work, but the pool functions without it for a while. Time logs rather than clinical judgement, so it teaches a different skill from the rest of E/M.
A24: TELEHEALTH — HC Coverage Matrix parent: 3% | F24: =IF(ROUND(SUMIF($B$5:$B$36,"Telehealth",$F$5:$F$36),6)=0.03,"OK — topics sum to the 3% parent","CHECK — topics do not sum to the 3% parent")
A25: EM-15 | B25: Telehealth | C25: Telehealth and virtual services | D25: Office visits delivered by telehealth, plus audio-only services, virtual check-ins and e-visits, where place of service and modifier decide payment. | E25: — | F25: 0.03 | G25: =ROUND(F25*$B$2,0) | H25: P3 | I25: Moderate-led | J25: C6 Customer escalations | K25: Place of service selection, telehealth modifiers (93, 95, FQ, FR), audio-only eligibility, time or MDM level, originating site | L25: The rules move faster than any other part of E/M, so these charts date quickly. Tag the code-set version carefully and expect to refresh this topic every cycle.
A26: INPATIENT AND OBSERVATION — HC Coverage Matrix parent: 18% | F26: =IF(ROUND(SUMIF($B$5:$B$36,"Inpatient and observation",$F$5:$F$36),6)=0.18,"OK — topics sum to the 18% parent","CHECK — topics do not sum to the 18% parent")
A27: EM-16 | B27: Inpatient and observation | C27: Initial hospital inpatient or observation care (99221-99223) | D27: The first encounter by the admitting provider, levelled on MDM, including the merge of inpatient and observation into one code family. | E27: ED-initiated observation by the ED physician — ED Profee (EDP-11) | F27: 0.06 | G27: =ROUND(F27*$B$2,0) | H27: P1 | I27: Moderate-led | J27: C1 High error rate | K27: Initial versus subsequent determination, COPA, Data Review, Risk, the admission date rule, inpatient and observation sharing one family | L27: The inpatient ladder is distinct from both office ladders; a chart coded on the wrong ladder is a classifier error, not a level error.
A28: EM-17 | B28: Inpatient and observation | C28: Subsequent hospital inpatient or observation care (99231-99233) | D28: Daily visits, levelled by whether the patient is stable, responding inadequately, or unstable. | E28: — | F28: 0.06 | G28: =ROUND(F28*$B$2,0) | H28: P1 | I28: Moderate-led | J28: C1 High error rate | K28: Subsequent care level criteria, interval history, COPA for an inadequately responding problem, Risk | L28: The highest-volume inpatient topic and where the level is most often defaulted to 99232 regardless of what the note supports.
A29: EM-18 | B29: Inpatient and observation | C29: Discharge day management (99238 / 99239) | D29: Discharge services, where total time on the discharge date decides between the two codes. | E29: Same-day admit and discharge — EM-19 | F29: 0.04 | G29: =ROUND(F29*$B$2,0) | H29: P1 | I29: Moderate-led | J29: C7 Denial trends | K29: The 30-minute threshold, what counts toward discharge time, the discharge date rule, who may report it | L29: Time-based rather than MDM-based. The documented time is frequently absent, in which case the lower code is the only defensible answer.
A30: EM-19 | B30: Inpatient and observation | C30: Same-day admission and discharge (99234-99236) | D30: Encounters where the patient is admitted and discharged on the same calendar date, which is its own code family rather than an initial visit plus a discharge. | E30: — | F30: 0.02 | G30: =ROUND(F30*$B$2,0) | H30: P2 | I30: Complex-led | J30: C1 High error rate | K30: Same-date criteria, the 8-hour rule, MDM level, why the initial-plus-discharge pairing is wrong here | L30: Low volume and high error rate: coders reach for 99221 plus 99238 because that is what the encounter looks like.
A31: CRITICAL CARE AND NEONATAL INTENSIVE CARE — HC Coverage Matrix parent: 5% | F31: =IF(ROUND(SUMIF($B$5:$B$36,"Critical care and neonatal intensive care",$F$5:$F$36),6)=0.05,"OK — topics sum to the 5% parent","CHECK — topics do not sum to the 5% parent")
A32: EM-20 | B32: Critical care and neonatal intensive care | C32: Inpatient critical care (99291 / 99292) | D32: Critical care delivered on the floor or in the ICU, with documented time, organ-system failure, and the bundled-service list. | E32: Critical care in the emergency department — ED Profee (EDP-08) | F32: 0.03 | G32: =ROUND(F32*$B$2,0) | H32: P2 | I32: Complex-led | J32: C2 High dollar value | K32: Critical care qualification, time documentation and the 30-minute floor, bundled versus separately reportable procedures, same-day E/M by the same provider | L32: Critical care sits outside every ladder in em_levels.py. This is the INPATIENT topic — ED critical care belongs to ED Profee, and the two must not share charts, because ED Facility, ED Profee, ED Single Path and E/M are four separate populations.
A33: EM-21 | B33: Critical care and neonatal intensive care | C33: Neonatal and paediatric critical care (99468-99476) | D33: NICU and PICU per-diem critical care, where one code covers the calendar day and age bands decide the family. | E33: — | F33: 0.02 | G33: =ROUND(F33*$B$2,0) | H33: P3 | I33: Complex-led | J33: C6 Customer escalations | K33: Per-diem versus time-based critical care, age band selection, initial versus subsequent day, what the per diem bundles | L33: Per-diem coding is the opposite of everything else in this specialty — time does not accumulate and the day is the unit. Low volume, so it is the one P4 topic, but the per-diem logic is unlike anything else in the pool.
A34: CONSULTATIONS — HC Coverage Matrix parent: 4% | F34: =IF(ROUND(SUMIF($B$5:$B$36,"Consultations",$F$5:$F$36),6)=0.04,"OK — topics sum to the 4% parent","CHECK — topics do not sum to the 4% parent")
A35: EM-22 | B35: Consultations | C35: Office and outpatient consultations (99242-99245) | D35: Outpatient consultations where the request, the reason for it and the report back must all be documented, and the payer must recognise consultation codes at all. | E35: — | F35: 0.02 | G35: =ROUND(F35*$B$2,0) | H35: P2 | I35: Complex-led | J35: C6 Customer escalations | K35: The three Rs (request, reason, report), consultation versus transfer of care, payer recognition, COPA, Data Review, Risk | L35: Consults are off-ladder for planting: em_levels.py knows three ladders plus critical care, so a consult level error is not a near miss along any of them. The commonest real error is billing a consult where care was simply transferred.
A36: EM-23 | B36: Consultations | C36: Inpatient consultations (99252-99255) | D36: Inpatient and observation consultations, including the distinction from an initial hospital visit by a provider taking over care. | E36: Initial hospital care by the admitting provider — EM-16 | F36: 0.02 | G36: =ROUND(F36*$B$2,0) | H36: P2 | I36: Complex-led | J36: C6 Customer escalations | K36: The three Rs, consultant versus admitting provider, concurrent care documentation, MDM level | L36: Two providers seeing the patient the same day is legitimate concurrent care, and the record has to show the different purpose.
A37: TOTAL | F37: =SUM(F5:F36) | G37: =SUM(G5:G36) | H37: Weights must total 100%
A39: Shaded Topic %% cells are the only editable numbers on this sheet. Target charts recalculates from the pool on Specialty Summary. Edit a weight and the category check in its band row will read CHECK until the other weights in that category are rebalanced — the sheet is built to refuse a topic that quietly grows at its neighbours' expense.
A40: Target charts is a ceiling, not a quota to fill at any cost. Where eligible supply genuinely is not there — a topic narrowed by exclusion X2, or a low-volume case type — report it as constrained in the gap review rather than substituting charts from an adjacent topic.
A41: Variance in the strip above is rounding drift between the sum of topic targets and the pool. The pool is the authority.

Sheet SDS Topics
A1: SDS — ideal chart composition by topic
A2: Baseline pool | B2: ='Specialty Summary'!$C$9 | C2: Topics | D2: =COUNTA(A5:A24)-5 | E2: Allocated | F2: =SUM(G5:G24) | G2: Variance | H2: =F2-B2 | I2: Dimension: Service line
A4: Topic ID | B4: Coverage category | C4: Topic | D4: Scope — what counts here | E4: Not here (goes where instead) | F4: Topic % of pool | G4: Target charts | H4: Build priority | I4: Difficulty skew | J4: Primary sourcing channel | K4: Key elements the chart must exercise | L4: Notes
A5: ORTHOPAEDICS — HC Coverage Matrix parent: 25% | F5: =IF(ROUND(SUMIF($B$5:$B$24,"Orthopaedics",$F$5:$F$24),6)=0.25,"OK — topics sum to the 25% parent","CHECK — topics do not sum to the 25% parent")
A6: SDS-01 | B6: Orthopaedics | C6: Knee and shoulder arthroscopy | D6: Same-day arthroscopic procedures, including multiple compartments and procedures performed through one approach. | E6: Arthroplasty requiring admission — IP-DRG (IPD-20) | F6: 0.1 | G6: =ROUND(F6*$B$2,0) | H6: P2 | I6: Moderate-led | J6: C1 High error rate | K6: Multiple procedure bundling in one compartment, modifier 51 and 59, laterality, implant and device capture | L6: Separately reportable versus bundled within the same compartment is the recurring error.
A7: SDS-02 | B7: Orthopaedics | C7: Hand and foot procedures | D7: Tendon, nerve and small-joint procedures where the code is driven by the digit and the structure treated. | E7: — | F7: 0.08 | G7: =ROUND(F7*$B$2,0) | H7: P2 | I7: Moderate-led | J7: C8 Foundation | K7: Digit-specific modifiers, number of structures treated, laterality, bundling
A8: SDS-03 | B8: Orthopaedics | C8: Fracture care and hardware removal | D8: Closed and open reduction performed same-day, and removal of previously placed hardware. | E8: — | F8: 0.07 | G8: =ROUND(F8*$B$2,0) | H8: P2 | I8: Moderate-led | J8: C8 Foundation | K8: Reduction versus manipulation, global period, hardware removal coding, laterality
A9: GI / ENDOSCOPY — HC Coverage Matrix parent: 25% | F9: =IF(ROUND(SUMIF($B$5:$B$24,"GI / endoscopy",$F$5:$F$24),6)=0.25,"OK — topics sum to the 25% parent","CHECK — topics do not sum to the 25% parent")
A10: SDS-04 | B10: GI / endoscopy | C10: Screening versus diagnostic colonoscopy | D10: Colonoscopies where the indication decides the code and the modifier: screening, screening converted to diagnostic, and surveillance. | E10: — | F10: 0.1 | G10: =ROUND(F10*$B$2,0) | H10: P2 | I10: Moderate-led | J10: C7 Denial trends | K10: Screening versus diagnostic determination, modifier 33 and PT, diagnosis sequencing, patient liability consequence | L10: A screening that converts to diagnostic changes both the code and the patient's liability. The highest-frequency denial topic in SDS.
A11: SDS-05 | B11: GI / endoscopy | C11: Colonoscopy with polypectomy — technique-driven coding | D11: Polyp removal where the technique used (snare, hot biopsy, cold forceps, EMR) decides the code, including multiple techniques in one session. | E11: — | F11: 0.08 | G11: =ROUND(F11*$B$2,0) | H11: P2 | I11: Complex-led | J11: C1 High error rate | K11: Technique-specific code selection, one code per technique rule, modifier 59, diagnosis linkage | L11: Coders routinely report one code per polyp rather than one per technique; a clean error to plant.
A12: SDS-06 | B12: GI / endoscopy | C12: EGD and combined upper and lower endoscopy | D12: Upper endoscopy alone and EGD performed with colonoscopy in the same session. | E12: — | F12: 0.07 | G12: =ROUND(F12*$B$2,0) | H12: P2 | I12: Moderate-led | J12: C8 Foundation | K12: Multiple endoscopy rules, modifier 51, base code selection, diagnosis linkage
A13: OPHTHALMOLOGY — HC Coverage Matrix parent: 15% | F13: =IF(ROUND(SUMIF($B$5:$B$24,"Ophthalmology",$F$5:$F$24),6)=0.15,"OK — topics sum to the 15% parent","CHECK — topics do not sum to the 15% parent")
A14: SDS-07 | B14: Ophthalmology | C14: Cataract extraction with IOL | D14: Routine and complex cataract extraction, including the documentation that distinguishes complex from routine. | E14: — | F14: 0.08 | G14: =ROUND(F14*$B$2,0) | H14: P2 | I14: Basic-led | J14: C8 Foundation | K14: Complex versus routine criteria, laterality, staged bilateral procedures, device capture | L14: High volume and largely formulaic, which makes it a reliable Basic-tier source.
A15: SDS-08 | B15: Ophthalmology | C15: Intravitreal injections and retinal laser | D15: Injection and laser procedures, often bilateral and repeated on a schedule. | E15: — | F15: 0.04 | G15: =ROUND(F15*$B$2,0) | H15: P2 | I15: Moderate-led | J15: C7 Denial trends | K15: Bilateral and laterality modifiers, repeat service within a period, drug units, diagnosis linkage
A16: SDS-09 | B16: Ophthalmology | C16: Oculoplastic and other eye procedures | D16: Lid, lacrimal and strabismus procedures where functional versus cosmetic intent decides coverage. | E16: — | F16: 0.03 | G16: =ROUND(F16*$B$2,0) | H16: P3 | I16: Complex-led | J16: C7 Denial trends | K16: Functional versus cosmetic documentation, laterality, bundling, diagnosis supporting medical necessity
A17: PAIN MANAGEMENT — HC Coverage Matrix parent: 15% | F17: =IF(ROUND(SUMIF($B$5:$B$24,"Pain management",$F$5:$F$24),6)=0.15,"OK — topics sum to the 15% parent","CHECK — topics do not sum to the 15% parent")
A18: SDS-10 | B18: Pain management | C18: Epidural and facet joint injections | D18: Injections where the spinal level, the number of levels and the laterality all drive the code and the units. | E18: — | F18: 0.08 | G18: =ROUND(F18*$B$2,0) | H18: P2 | I18: Complex-led | J18: C1 High error rate | K18: Level counting and add-on codes, bilateral reporting, imaging guidance bundling, MUE limits | L18: Level counting against the MUE limit is the specific failure; the units are where it goes wrong, not the base code.
A19: SDS-11 | B19: Pain management | C19: Radiofrequency ablation and nerve blocks | D19: Ablation and block procedures by nerve and level, including the diagnostic block that precedes ablation. | E19: — | F19: 0.07 | G19: =ROUND(F19*$B$2,0) | H19: P2 | I19: Complex-led | J19: C7 Denial trends | K19: Nerve-specific code selection, level and laterality units, prior diagnostic block requirement, imaging bundling
A20: OTHER SURGICAL — HC Coverage Matrix parent: 20% | F20: =IF(ROUND(SUMIF($B$5:$B$24,"Other surgical",$F$5:$F$24),6)=0.2,"OK — topics sum to the 20% parent","CHECK — topics do not sum to the 20% parent")
A21: SDS-12 | B21: Other surgical | C21: General surgery — hernia repair, cholecystectomy, excisions | D21: Same-day general surgery, including hernia repair by type and approach and lesion excision by size and margin. | E21: Cases requiring admission — IP-DRG (IPD-17) | F21: 0.07 | G21: =ROUND(F21*$B$2,0) | H21: P2 | I21: Moderate-led | J21: C8 Foundation | K21: Hernia type, approach and reducibility, lesion size including margins, approach character, bundling
A22: SDS-13 | B22: Other surgical | C22: Gynaecology — hysteroscopy, D&C, laparoscopy | D22: Same-day gynaecological surgery, including diagnostic-to-operative conversion. | E22: Delivery admissions — IP-DRG (IPD-01 / IPD-15) | F22: 0.05 | G22: =ROUND(F22*$B$2,0) | H22: P2 | I22: Moderate-led | J22: C8 Foundation | K22: Diagnostic versus operative, bundling within one approach, modifier 59, diagnosis linkage
A23: SDS-14 | B23: Other surgical | C23: ENT — tonsillectomy, sinus surgery, myringotomy | D23: Airway and sinus procedures where bilateral reporting and multiple sinuses drive the units. | E23: — | F23: 0.04 | G23: =ROUND(F23*$B$2,0) | H23: P3 | I23: Moderate-led | J23: C8 Foundation | K23: Bilateral and multiple-site reporting, age-banded code selection, bundling
A24: SDS-15 | B24: Other surgical | C24: Urology — cystoscopy, TURP, stone procedures | D24: Same-day urological procedures, including cystoscopy as a base for a more extensive service. | E24: Procedures requiring admission — IP-DRG (IPD-22) | F24: 0.04 | G24: =ROUND(F24*$B$2,0) | H24: P2 | I24: Moderate-led | J24: C8 Foundation | K24: Base versus more extensive procedure, bundling of the cystoscopy, laterality, stent placement
A25: TOTAL | F25: =SUM(F5:F24) | G25: =SUM(G5:G24) | H25: Weights must total 100%
A27: Shaded Topic %% cells are the only editable numbers on this sheet. Target charts recalculates from the pool on Specialty Summary. Edit a weight and the category check in its band row will read CHECK until the other weights in that category are rebalanced — the sheet is built to refuse a topic that quietly grows at its neighbours' expense.
A28: Target charts is a ceiling, not a quota to fill at any cost. Where eligible supply genuinely is not there — a topic narrowed by exclusion X2, or a low-volume case type — report it as constrained in the gap review rather than substituting charts from an adjacent topic.
A29: Variance in the strip above is rounding drift between the sum of topic targets and the pool. The pool is the authority.

Sheet Surgery Topics
A1: Surgery — ideal chart composition by topic
A2: Baseline pool | B2: ='Specialty Summary'!$C$10 | C2: Topics | D2: =COUNTA(A5:A17)-2 | E2: Allocated | F2: =SUM(G5:G17) | G2: Variance | H2: =F2-B2 | I2: Dimension: Service line
A4: Topic ID | B4: Coverage category | C4: Topic | D4: Scope — what counts here | E4: Not here (goes where instead) | F4: Topic % of pool | G4: Target charts | H4: Build priority | I4: Difficulty skew | J4: Primary sourcing channel | K4: Key elements the chart must exercise | L4: Notes
A5: HIGH-VOLUME SERVICE LINES — HC Coverage Matrix parent: 64% | F5: =IF(ROUND(SUMIF($B$5:$B$17,"High-volume service lines",$F$5:$F$17),6)=0.64,"OK — topics sum to the 64% parent","CHECK — topics do not sum to the 64% parent")
A6: SUR-01 | B6: High-volume service lines | C6: General surgery — hernia, cholecystectomy, appendectomy, bowel | D6: Professional surgical coding for general-surgery cases across settings, including laparoscopic-to-open conversion. | E6: Same-day minor excisions — SDS-12 | F6: 0.18 | G6: =ROUND(F6*$B$2,0) | H6: P2 | I6: Moderate-led | J6: C8 Foundation | K6: Approach and conversion coding, multiple procedure bundling, modifier 51 and 59, global period | L6: Conversion from laparoscopic to open is coded to the completed approach, not both; a clean error to plant.
A7: SUR-02 | B7: High-volume service lines | C7: Orthopaedics — arthroplasty, arthroscopy, fracture fixation | D7: Professional coding for orthopaedic surgery including revision arthroplasty and multi-level spinal instrumentation. | E7: Same-day arthroscopy — SDS-01 | F7: 0.18 | G7: =ROUND(F7*$B$2,0) | H7: P2 | I7: Complex-led | J7: C2 High dollar value | K7: Primary versus revision, component-level coding, level counting and add-ons, laterality, modifier 62 co-surgeon
A8: SUR-03 | B8: High-volume service lines | C8: Cardiothoracic and vascular | D8: Open cardiac, thoracic and vascular procedures, including graft harvest and multi-vessel work. | E8: — | F8: 0.1 | G8: =ROUND(F8*$B$2,0) | H8: P2 | I8: Complex-led | J8: C2 High dollar value | K8: Number of grafts and vessels, harvest as a separate procedure, modifier 62 and 80, bundling of access | L8: Highest reimbursement per chart. Counting vessels and reporting harvest separately are the two recurring errors.
A9: SUR-04 | B9: High-volume service lines | C9: Neurosurgery — cranial and spine | D9: Cranial procedures and spinal decompression, fusion and instrumentation, where levels and approaches multiply. | E9: — | F9: 0.1 | G9: =ROUND(F9*$B$2,0) | H9: P2 | I9: Complex-led | J9: C2 High dollar value | K9: Level counting across decompression and fusion, approach-specific codes, add-on hierarchy, co-surgeon modifiers
A10: SUR-05 | B10: High-volume service lines | C10: Gynaecology and obstetric surgery | D10: Hysterectomy by approach and weight, caesarean delivery, and oncological gynaecological surgery. | E10: Same-day gynaecology — SDS-13 | F10: 0.08 | G10: =ROUND(F10*$B$2,0) | H10: P2 | I10: Moderate-led | J10: C8 Foundation | K10: Approach and specimen weight, bundled oophorectomy, global obstetric package, modifier 22
A11: SPECIALTY AND CROSS-CUTTING — HC Coverage Matrix parent: 36% | F11: =IF(ROUND(SUMIF($B$5:$B$17,"Specialty and cross-cutting",$F$5:$F$17),6)=0.36,"OK — topics sum to the 36% parent","CHECK — topics do not sum to the 36% parent")
A12: SUR-06 | B12: Specialty and cross-cutting | C12: Urology | D12: Open and endoscopic urological surgery including prostatectomy, nephrectomy and reconstruction. | E12: Same-day cystoscopy — SDS-15 | F12: 0.08 | G12: =ROUND(F12*$B$2,0) | H12: P2 | I12: Moderate-led | J12: C8 Foundation | K12: Approach, bundling of the endoscopic base, laterality, robotic assistance reporting
A13: SUR-07 | B13: Specialty and cross-cutting | C13: ENT and head and neck | D13: Airway, sinus, thyroid and head-and-neck oncological surgery, including neck dissection levels. | E13: — | F13: 0.07 | G13: =ROUND(F13*$B$2,0) | H13: P2 | I13: Moderate-led | J13: C8 Foundation | K13: Bilateral and multiple-site reporting, neck dissection extent, bundling, modifier 59
A14: SUR-08 | B14: Specialty and cross-cutting | C14: Plastics and reconstructive | D14: Flaps, grafts and reconstruction, where defect size and donor site both carry codes, and intent decides coverage. | E14: — | F14: 0.06 | G14: =ROUND(F14*$B$2,0) | H14: P2 | I14: Complex-led | J14: C7 Denial trends | K14: Defect size and site, donor site closure, functional versus cosmetic documentation, staged procedure modifiers
A15: SUR-09 | B15: Specialty and cross-cutting | C15: Ophthalmic surgery | D15: Retinal, corneal and glaucoma surgery beyond routine same-day cataract work. | E15: Routine cataract — SDS-07 | F15: 0.05 | G15: =ROUND(F15*$B$2,0) | H15: P3 | I15: Moderate-led | J15: C8 Foundation | K15: Laterality and staged bilateral work, bundling, global period, device capture
A16: SUR-10 | B16: Specialty and cross-cutting | C16: Transplant and complex multi-specialty cases | D16: Transplant, multi-team and multi-stage procedures where more than one surgeon reports a service. | E16: — | F16: 0.04 | G16: =ROUND(F16*$B$2,0) | H16: P3 | I16: Complex-led | J16: C2 High dollar value | K16: Modifier 62, 66 and 80, donor versus recipient coding, staged procedure reporting
A17: SUR-11 | B17: Specialty and cross-cutting | C17: Global period and staged procedure scenarios | D17: Returns to theatre, unrelated procedures during a global period, and staged work, where the modifier is the answer. | E17: — | F17: 0.06 | G17: =ROUND(F17*$B$2,0) | H17: P2 | I17: Complex-led | J17: C1 High error rate | K17: Modifiers 58, 76, 77, 78 and 79, global period boundaries, related versus unrelated determination | L17: A modifier-selection topic rather than a code-selection one. Which of 58, 78 and 79 applies is the whole question, and getting it wrong changes payment entirely.
A18: TOTAL | F18: =SUM(F5:F17) | G18: =SUM(G5:G17) | H18: Weights must total 100%
A20: Shaded Topic %% cells are the only editable numbers on this sheet. Target charts recalculates from the pool on Specialty Summary. Edit a weight and the category check in its band row will read CHECK until the other weights in that category are rebalanced — the sheet is built to refuse a topic that quietly grows at its neighbours' expense.
A21: Target charts is a ceiling, not a quota to fill at any cost. Where eligible supply genuinely is not there — a topic narrowed by exclusion X2, or a low-volume case type — report it as constrained in the gap review rather than substituting charts from an adjacent topic.
A22: Variance in the strip above is rounding drift between the sum of topic targets and the pool. The pool is the authority.

Sheet ED Single Path Topics
A1: ED Single Path — ideal chart composition by topic
A2: Baseline pool | B2: ='Specialty Summary'!$C$11 | C2: Topics | D2: =COUNTA(A5:A18)-6 | E2: Allocated | F2: =SUM(G5:G18) | G2: Variance | H2: =F2-B2 | I2: Dimension: Acuity ladder (facility and profee on one chart)
A4: Topic ID | B4: Coverage category | C4: Topic | D4: Scope — what counts here | E4: Not here (goes where instead) | F4: Topic % of pool | G4: Target charts | H4: Build priority | I4: Difficulty skew | J4: Primary sourcing channel | K4: Key elements the chart must exercise | L4: Notes
A5: LOW ACUITY — HC Coverage Matrix parent: 7% | F5: =IF(ROUND(SUMIF($B$5:$B$18,"Low acuity",$F$5:$F$18),6)=0.07,"OK — topics sum to the 7% parent","CHECK — topics do not sum to the 7% parent")
A6: ESP-01 | B6: Low acuity | C6: Low acuity — levels 1–2 both components | D6: Single-path coding of a low-acuity ED encounter: facility level and professional level assigned from the same record. | E6: — | F6: 0.07 | G6: =ROUND(F6*$B$2,0) | H6: P2 | I6: Basic-led | J6: C8 Foundation | K6: Facility acuity tool and professional MDM applied to one record, diagnosis specificity, disposition | L6: Mirrors EDF-01 and EDP-01, but the charts are not shared between pools: a single-path chart is graded on both components at once and belongs only here.
A7: MODERATE — HC Coverage Matrix parent: 16% | F7: =IF(ROUND(SUMIF($B$5:$B$18,"Moderate",$F$5:$F$18),6)=0.16,"OK — topics sum to the 16% parent","CHECK — topics do not sum to the 16% parent")
A8: ESP-02 | B8: Moderate | C8: Moderate — level 3 both components | D8: Moderate presentations with limited workup, coded for facility and professional components together. | E8: — | F8: 0.16 | G8: =ROUND(F8*$B$2,0) | H8: P2 | I8: Basic-led | J8: C8 Foundation | K8: Facility level criteria, professional MDM (COPA, Data, Risk), diagnosis specificity | L8: Mirrors EDF-04 and EDP-02.
A9: LEVEL 4 — HC Coverage Matrix parent: 18% | F9: =IF(ROUND(SUMIF($B$5:$B$18,"Level 4",$F$5:$F$18),6)=0.18,"OK — topics sum to the 18% parent","CHECK — topics do not sum to the 18% parent")
A10: ESP-03 | B10: Level 4 | C10: Level 4 both components | D10: Multi-system or extensively worked-up presentations at level 4 on both components. | E10: — | F10: 0.18 | G10: =ROUND(F10*$B$2,0) | H10: P2 | I10: Moderate-led | J10: C1 High error rate | K10: Facility level at the 4/5 boundary, professional MDM and the 2-of-3 rule, comorbidity capture | L10: Mirrors EDF-08 to EDF-10 and EDP-04.
A11: LEVEL 5 — HC Coverage Matrix parent: 21% | F11: =IF(ROUND(SUMIF($B$5:$B$18,"Level 5",$F$5:$F$18),6)=0.21,"OK — topics sum to the 21% parent","CHECK — topics do not sum to the 21% parent")
A12: ESP-04 | B12: Level 5 | C12: Level 5 both components | D12: High-acuity encounters short of critical care, coded at level 5 on both components. | E12: Documented critical care time — ESP-05 | F12: 0.21 | G12: =ROUND(F12*$B$2,0) | H12: P2 | I12: Complex-led | J12: C1 High error rate | K12: Facility level 5 criteria, professional COPA, data and risk at the highest level, diagnosis sequencing | L12: Mirrors EDF-13 and EDP-06. The largest topic in this pool, as it is on both parent ladders.
A13: CRITICAL CARE — HC Coverage Matrix parent: 18% | F13: =IF(ROUND(SUMIF($B$5:$B$18,"Critical care",$F$5:$F$18),6)=0.18,"OK — topics sum to the 18% parent","CHECK — topics do not sum to the 18% parent")
A14: ESP-05 | B14: Critical care | C14: Critical care — both components | D14: Critical care encounters where the facility and professional components are both reported from one record. | E14: — | F14: 0.18 | G14: =ROUND(F14*$B$2,0) | H14: P2 | I14: Complex-led | J14: C2 High dollar value | K14: Critical care qualification, bundled versus separately reportable procedures, facility level interaction, diagnosis sequencing | L14: Whether the condition qualified as critical care at all is the training point. The 99292 unit count follows from the time and is not planted.
A15: CROSS-CUTTING — HC Coverage Matrix parent: 20% | F15: =IF(ROUND(SUMIF($B$5:$B$18,"Cross-cutting",$F$5:$F$18),6)=0.2,"OK — topics sum to the 20% parent","CHECK — topics do not sum to the 20% parent")
A16: ESP-06 | B16: Cross-cutting | C16: ED procedures across both components | D16: Encounters with a procedure, where the facility charge, the professional procedure code and modifier 25 interact. | E16: — | F16: 0.1 | G16: =ROUND(F16*$B$2,0) | H16: P2 | I16: Moderate-led | J16: C1 High error rate | K16: Procedure code selection, modifier 25 and 59 on the professional side, facility charge capture, bundling
A17: ESP-07 | B17: Cross-cutting | C17: Observation and admission decisions | D17: Encounters converting to observation or inpatient, where the two components diverge on what is reportable. | E17: — | F17: 0.06 | G17: =ROUND(F17*$B$2,0) | H17: P2 | I17: Complex-led | J17: C7 Denial trends | K17: Observation hour counting on the facility side, which professional code family applies, status determination
A18: ESP-08 | B18: Cross-cutting | C18: Facility and professional level divergence | D18: Encounters where the correct facility level and the correct professional level are legitimately different, because one is driven by resource use and the other by medical decision making. | E18: — | F18: 0.04 | G18: =ROUND(F18*$B$2,0) | H18: P3 | I18: Complex-led | J18: C6 Customer escalations | K18: Both level determinations on one record, why they diverge, documentation supporting each | L18: The reason single path is its own specialty rather than a view of the other two. A coder who assumes the two levels must match is the error this topic exists to find.
A19: TOTAL | F19: =SUM(F5:F18) | G19: =SUM(G5:G18) | H19: Weights must total 100%
A21: Shaded Topic %% cells are the only editable numbers on this sheet. Target charts recalculates from the pool on Specialty Summary. Edit a weight and the category check in its band row will read CHECK until the other weights in that category are rebalanced — the sheet is built to refuse a topic that quietly grows at its neighbours' expense.
A22: Target charts is a ceiling, not a quota to fill at any cost. Where eligible supply genuinely is not there — a topic narrowed by exclusion X2, or a low-volume case type — report it as constrained in the gap review rather than substituting charts from an adjacent topic.
A23: Variance in the strip above is rounding drift between the sum of topic targets and the pool. The pool is the authority.

Sheet Coverage Dimensions
A1: Coverage Dimensions — carried from the HC model
A2: Section 6 of PracticeLab_HC.xlsx, unchanged, plus the three specialties it does not cover. This is the parent layer every topic sheet decomposes.
A4: Specialty | B4: Dimension | C4: Category | D4: Target % | E4: Target charts | F4: Source and note
A5: IP-DRG | B5: DRG type | C5: Medical DRGs (top client volume) | D5: 0.55 | E5: 381 | F5: Carried from HC Chart Selection section 6
C6: Surgical DRGs (top client volume) | D6: 0.45 | E6: 312 | F6: Carried from HC Chart Selection section 6
B7: Severity | C7: Without CC/MCC | D7: 0.3 | E7: 208 | F7: Carried from HC Chart Selection section 6. A second, independent dimension: it cuts across every topic rather than sitting under one, so it is not decomposed on the topic sheet.
C8: With CC | D8: 0.35 | E8: 243 | F8: Carried from HC Chart Selection section 6
C9: With MCC | D9: 0.35 | E9: 243 | F9: Carried from HC Chart Selection section 6
B10: Must include | C10: POA indicators · principal diagnosis sequencing · ICD-10-PCS procedures · query opportunities | F10: Carried from HC Chart Selection section 6. Every one of these appears in the elements column of at least one IP-DRG topic.
A11: ED Facility | B11: Facility level | C11: Levels 1–2 | D11: 0.2 | E11: 141 | F11: Carried from HC Chart Selection section 6
C12: Level 3 | D12: 0.3 | E12: 211 | F12: Carried from HC Chart Selection section 6
C13: Level 4 | D13: 0.3 | E13: 211 | F13: Carried from HC Chart Selection section 6
C14: Level 5 / critical care | D14: 0.2 | E14: 141 | F14: Carried from HC Chart Selection section 6
B15: Must include | C15: Injuries · infusions and injections · ED procedures · observation | F15: Carried from HC Chart Selection section 6
A16: E/M | B16: Service family | C16: Office / outpatient visits | D16: 0.42 | E16: 173 | F16: Not in the HC model — set 2026-10-15 with this workbook. REPLACES the HC Level split as this specialty's parent dimension — see note below.
C17: Time-based and prolonged services | D17: 0.04 | E17: 17 | F17: Not in the HC model — set 2026-10-15 with this workbook
C18: Preventive and wellness | D18: 0.14 | E18: 58 | F18: Not in the HC model — set 2026-10-15 with this workbook
C19: Office procedures with an E/M | D19: 0.05 | E19: 21 | F19: Not in the HC model — set 2026-10-15 with this workbook
C20: Care management and transitional care | D20: 0.05 | E20: 21 | F20: Not in the HC model — set 2026-10-15 with this workbook
C21: Telehealth | D21: 0.03 | E21: 12 | F21: Not in the HC model — set 2026-10-15 with this workbook
C22: Inpatient and observation | D22: 0.18 | E22: 74 | F22: Not in the HC model — set 2026-10-15 with this workbook
C23: Critical care and neonatal intensive care | D23: 0.05 | E23: 21 | F23: Not in the HC model — set 2026-10-15 with this workbook
C24: Consultations | D24: 0.04 | E24: 17 | F24: Not in the HC model — set 2026-10-15 with this workbook
B25: Level (cross-cutting) | C25: Low (levels 2–3) | D25: 0.35 | E25: 145 | F25: Carried from HC Chart Selection section 6. Now checked ACROSS the pool rather than decomposed, because AWV, TCM, CCM, telehealth and NICU per-diem codes are not levels at all.
C26: Moderate (level 4) | D26: 0.4 | E26: 165 | F26: Carried from HC Chart Selection section 6
C27: High (level 5) | D27: 0.25 | E27: 103 | F27: Carried from HC Chart Selection section 6. Runs 10-15% of production; the pool holds 7% deliberately, since a training pool weights the hard calls rather than mirroring the mix.
B28: Method (cross-cutting) | C28: MDM-based | D28: 0.8 | E28: 330 | F28: Carried from HC Chart Selection section 6. Preventive visits, consults, per-diem neonatal care and time-levelled visits are not graded on medical decision making at all, so applicable_weights drops the MDM weights and the form is resolved per chart.
C29: Time-based | D29: 0.2 | E29: 83 | F29: Carried from HC Chart Selection section 6. Topics EM-07, EM-14, EM-18 and EM-21 are where these charts come from.
B30: Must include | C30: New versus established · office versus hospital · modifier 25 · AWV initial versus subsequent · telehealth place of service | F30: Not in the HC model — set 2026-10-15 with this workbook
A31: SDS | B31: Service line | C31: Orthopaedics | D31: 0.25 | E31: 33 | F31: Carried from HC Chart Selection section 6
C32: GI / endoscopy | D32: 0.25 | E32: 33 | F32: Carried from HC Chart Selection section 6
C33: Ophthalmology | D33: 0.15 | E33: 20 | F33: Carried from HC Chart Selection section 6
C34: Pain management | D34: 0.15 | E34: 20 | F34: Carried from HC Chart Selection section 6
C35: Other surgical | D35: 0.2 | E35: 26 | F35: Carried from HC Chart Selection section 6
B36: Must include | C36: Modifiers (bilateral, distinct procedure) · implants and devices | F36: Carried from HC Chart Selection section 6
A37: ED Profee | B37: ED E/M level | C37: Low acuity (99281 / 99282) | D37: 0.08 | E37: 32 | F37: Not in the HC model — set 2026-10-15 with this workbook
C38: Moderate (99283) | D38: 0.18 | E38: 72 | F38: Not in the HC model — set 2026-10-15 with this workbook
C39: Level 4 (99284) | D39: 0.2 | E39: 80 | F39: Not in the HC model — set 2026-10-15 with this workbook
C40: Level 5 (99285) | D40: 0.24 | E40: 96 | F40: Not in the HC model — set 2026-10-15 with this workbook
C41: Critical care (99291 / 99292) | D41: 0.12 | E41: 48 | F41: Not in the HC model — set 2026-10-15 with this workbook
C42: Cross-cutting (procedures, observation, split/shared) | D42: 0.18 | E42: 72 | F42: Not in the HC model — set 2026-10-15 with this workbook
B43: Must include | C43: Modifier 25 · the 99285 versus 99291 boundary · split and shared documentation | F43: Not in the HC model — set 2026-10-15 with this workbook. The boundary charts only plant if AnswerKey.cc_boundary is set to borderline.
A44: Surgery | B44: Service line | C44: High-volume service lines (general, ortho, CT/vascular, neuro, gynae) | D44: 0.64 | E44: 192 | F44: Not in the HC model — set 2026-10-15 with this workbook
C45: Specialty and cross-cutting | D45: 0.36 | E45: 108 | F45: Not in the HC model — set 2026-10-15 with this workbook
B46: Must include | C46: Global period and staged procedure modifiers · co-surgeon and assistant modifiers · laterality | F46: Not in the HC model — set 2026-10-15 with this workbook
A47: ED Single Path | B47: Acuity ladder | C47: Low acuity | D47: 0.08 | E47: 24 | F47: Not in the HC model — set 2026-10-15 with this workbook
C48: Moderate (level 3) | D48: 0.18 | E48: 54 | F48: Not in the HC model — set 2026-10-15 with this workbook
C49: Level 4 | D49: 0.2 | E49: 60 | F49: Not in the HC model — set 2026-10-15 with this workbook
C50: Level 5 | D50: 0.22 | E50: 66 | F50: Not in the HC model — set 2026-10-15 with this workbook
C51: Critical care | D51: 0.12 | E51: 36 | F51: Not in the HC model — set 2026-10-15 with this workbook
C52: Cross-cutting | D52: 0.2 | E52: 60 | F52: Not in the HC model — set 2026-10-15 with this workbook
B53: Must include | C53: Both level determinations on one record · legitimate divergence between them · modifier 25 | F53: Not in the HC model — set 2026-10-15 with this workbook. Divergence is the reason single path is a specialty and not a view of the other two ED pools.
A55: E/M is the one specialty whose parent dimension is NOT the HC Coverage Matrix category. The HC matrix splits it by level (35/40/25) and method (80/20), but the trainers' own breakdown spans AWV, TCM, chronic care management, telehealth and neonatal per-diem codes, none of which has a level. Service family is therefore the parent and the level and method splits are checked across the pool, exactly as Severity is on IP-DRG. The HC percentages are unchanged — only their position in the hierarchy is.
A56: ED Facility, ED Profee and ED Single Path are three separate populations, not three views of one. The same encounter coded for the facility, coded professionally and coded single-path is three different charts; none of them belongs in the E/M pool, which is why the E/M dimension here has no ED setting. Confirmed 15 October 2026.
A57: Severity on IP-DRG and Method on E/M are cross-cutting dimensions: a chart has a CC/MCC status and an MDM-or-time basis whatever its topic. They are checked across the pool, not decomposed per topic, which is why the topic sheets carry one dimension each.
A58: Where a target percentage here changes, the matching band row on the topic sheet and its child weights must change together. The band row's check cell is what tells you they have come apart.

Sheet Tag Dictionary
A1: Required tags per chart
A2: HC Chart Selection section 7, plus the one field this workbook adds. A chart missing a mandatory tag is not classified and cannot appear in a gap report.
A4: Tag | B4: Mandatory | C4: What is captured | D4: Why it is needed
A5: Topic ID | B5: Yes — new | C5: The topic from this workbook, exactly one per chart (e.g. IPD-02, EDP-07). A chart spanning two topics is classified by the element its answer key turns on. | D5: The field this workbook adds. Without it a gap report can only be run at coverage-category level, which is where the HC model already stops — a category can look full while one topic inside it holds every chart.
A6: Specialty and coverage category | B6: Yes | C6: Specialty plus the coverage-matrix category the chart fills. | D6: HC section 7. The parent of the Topic ID; kept so the two layers can be reconciled.
A7: Difficulty tier | B7: Yes | C7: Basic, Moderate or Complex against the HC section 4 criteria. | D7: Drives the Week 1 / Week 2 mix. The topic sheet's skew column says what is plausible for a topic; this records what the chart actually is.
A8: Learning objective(s) | B8: Yes | C8: The specific guideline or skill the chart teaches. | D8: HC section 7's teaching-value test: a chart with nothing to teach does not enter the pool, however clean it is.
A9: Sourcing channel | B9: Yes | C9: Primary channel C1–C8 plus any secondary channels; for C1 and C7, the error or denial category targeted. | D9: Lets a topic gap be traced back to the report that would fill it.
A10: Source type and client | B10: Yes | C10: QA/QR-validated or PL re-coded; client or facility as a de-identified reference. | D10: Carries the HC 60/40 source split and the S2 client-diversity minimum of three clients per specialty.
A11: Guideline / code-set version | B11: Yes | C11: Fiscal year or code-set version the answer key is based on. | D11: The refresh depends on it: Oct 1 ICD-10 and IPPS, Jan 1 CPT, quarterly NCCI and OCE. A chart whose version is unknown cannot be refreshed, only rebuilt.
A12: Build and validation dates | B12: Yes | C12: When built, who validated, when approved. | D12: Second-level validation before publishing is required for every chart, and for PL re-coded charts it is the only check on the key.
A13: Usage count | B13: Yes | C13: Number of batches the chart has appeared in. | D13: Drives retirement, and enforces the rule that a chart may repeat across batches but never within one.
A14: Answer key presence | B14: Recommended | C14: Whether a validated key exists, and in which table it lives. | D14: E/M and ED Profee keys live in em_answer_keys, which has no row in answer_keys. A query joining only against the ordinary key table reports zero keys for every E/M chart — which once told a trainer who had just entered five keys that nothing could be graded.
A15: Authored error version(s) | B15: Recommended | C15: Whether the chart carries trainer-authored error sets for the auditor module, and how many versions. | D15: Version rotation keys on the chart's own use count, so the count has to be visible per chart. Hand-picked allocation is also the only mode that may pin a specific version.
A17: Enforce these per FIELD, not per chart record. A check asking whether a chart has tags passes as soon as one tag is present; anchor the check on each value, then delete that value and confirm the check fails.

Sheet Open Decisions
A1: Decisions
A2: Settled ones first, with what was decided. The open ones each change a number somebody else owns, so they are listed rather than resolved — nothing on the topic sheets depends on them being settled first.
A4: # | B4: Decision | C4: What is at stake, or what was decided | D4: Owner | E4: Status
A5: 1 | B5: ED Facility, ED Profee, ED Single Path and E/M are four separate chart populations | C5: Confirmed: an ED encounter coded for the facility, the same encounter coded professionally, and a single-path encounter are three different charts, and none of them belongs in the E/M pool. So the pools of 704, 400, 300 and 413 do not overlap and nothing is double-counted — but sourcing has to pull four distinct populations, and the E/M pool holding no ED setting is correct rather than an oversight. | D5: Confirmed by the user | E5: Settled 2026-10-15
A6: 2 | B6: E/M keeps no ED-setting share | C6: Follows from the above. ED E/M sits in ED Profee, the E/M topic list deliberately holds no ED setting, and the HC E/M pool of 413 is not oversized by it. | D6: Confirmed by the user | E6: Settled 2026-10-15
A7: 3 | B7: E/M is classified by service family, not by the HC level split | C7: Confirmed with the trainers on 2026-10-15. Their own breakdown of E/M spans annual wellness visits, transitional and chronic care management, telehealth, minor office procedures and neonatal per-diem critical care — none of which has an E/M level, so the HC matrix's level dimension cannot be the parent. Service family became the parent and the HC level (35/40/25) and method (80/20) splits are now checked across the pool rather than decomposed, the same treatment Severity gets on IP-DRG. No HC percentage changed; only its position in the hierarchy did. | D7: Confirmed by the user | E7: Settled 2026-10-15
A8: 4 | B8: E/M priorities are set, including a fourth priority band | C8: Level 3 and 4 office visits and the inpatient/observation trio are P1. Level 5 office, preventive and wellness, inpatient critical care and consultations are P2. Levels 1-2, minor procedures with an E/M, TCM, telehealth and NICU/PICU are P3. Chronic care management is P4, the first topic in the workbook to need a fourth band — real work, but the pool functions without it for a while. | D8: Confirmed by the user | E8: Settled 2026-10-15
A9: 5 | B9: Add ED Profee, Surgery and ED Single Path to the HC model | C9: Pools of 400, 300 and 300 were set here, outside the HC model. None of them has a +10% buffer calculation, a per-batch average, a batch count or a build-hour line. That is 1,000 charts the HC Specialty Grid, Chart Pool, FTE Demand and FTE Summary sheets do not know about — at HC's own build rates roughly 1,500 to 2,250 hours, close to a further FTE. Until they are added, the team size in that model is understated. | D9: Whoever owns the HC model | E9: Open
A10: 6 | B10: Set the cc_boundary flag policy for the 99285 / 99291 charts | C10: Topic EDP-07 exists for charts where the critical care call is genuinely arguable, and the auditor module only plants against them when a trainer has set AnswerKey.cc_boundary to borderline. Without a policy on who sets it and on what evidence, the topic fills with charts nothing is ever planted in. | D10: PL Trainer plus QR | E10: Open
A11: 7 | B11: Agree the constrained-supply topics | C11: IPD-13 (mental health), EDF-11 (behavioural health), IPD-16 (obstetric surgical) and IPD-24 (transplant) are narrowed by exclusion X2 or by case rarity. Each needs a stated floor below which it is reported as constrained rather than chased, so a gap report does not show a permanent red against a topic nobody can fill. | D11: PL Trainer plus Compliance for X2 | E11: Open
A12: 8 | B12: Decide how a topic-level gap report is produced | C12: Topic ID has to be a filterable field on the chart record for any of this to be measurable. HC section 9 sets the trigger at 80% of target reviewed monthly, which is not workable by hand across roughly 125 topics. | D12: PL Trainer plus the platform team | E12: Open
A13: 9 | B13: Extend the topic layer to Denials/Edits and Ancillary | C13: Both are deferred from this pass. Their HC pools (165 and 594) and coverage matrices stand, so they are classified at category level but not at topic level — 759 charts, a quarter of the HC total, outside this framework. | D13: PL Trainer | E13: Open
A14: 10 | B14: Confirm the difficulty skew per topic against real charts | C14: The skew column is a judgement about what a topic can plausibly hold, made before any chart was sourced. Once a few hundred charts are classified and tiered, compare the actual tier distribution per topic against the skew and correct the column, not the charts. | D14: PL Trainer, at the first refresh | E14: Open
